{
  "name": "Abbie Falls",
  "id": 1510737005,
  "albums": [
    {
      "name": "Life is just a temporary plan",
      "year": "2025",
      "release_date": "2025-12-12",
      "cover": "https://is1-ssl.mzstatic.com/image/thumb/Music221/v4/c0/0c/e9/c00ce995-ca85-71b6-717d-c361f0b4f952/cover.jpg/600x600bb.jpg",
      "tracks": [
        {
          "number": 1,
          "name": "FURY",
          "duration": "1:57"
        },
        {
          "number": 2,
          "name": "Black Void",
          "duration": "3:38"
        },
        {
          "number": 3,
          "name": "Victim",
          "duration": "4:21"
        },
        {
          "number": 4,
          "name": "descend.exe",
          "duration": "2:47"
        },
        {
          "number": 5,
          "name": "Purge",
          "duration": "3:13"
        },
        {
          "number": 6,
          "name": "Anomaly in G minor",
          "duration": "3:37"
        },
        {
          "number": 7,
          "name": "Chaos Disciples",
          "duration": "3:00"
        },
        {
          "number": 8,
          "name": "Approach of the Second Sun",
          "duration": "3:16"
        },
        {
          "number": 9,
          "name": "Hellbound",
          "duration": "3:40"
        },
        {
          "number": 10,
          "name": "unnatural order",
          "duration": "3:31"
        }
      ]
    },
    {
      "name": "No One's Above, No One's Below",
      "year": "2021",
      "release_date": "2021-05-20",
      "cover": "https://is1-ssl.mzstatic.com/image/thumb/Music125/v4/59/3e/ef/593eefab-7fc9-eeff-9541-50d70d3bd446/artwork.jpg/600x600bb.jpg",
      "tracks": [
        {
          "number": 1,
          "name": "No One's Below",
          "duration": "2:58"
        },
        {
          "number": 2,
          "name": "Mayday",
          "duration": "3:18"
        },
        {
          "number": 3,
          "name": "Amphisbaena",
          "duration": "3:04"
        },
        {
          "number": 4,
          "name": "No One's Above",
          "duration": "3:34"
        },
        {
          "number": 5,
          "name": "No One's Below (Instrumental)",
          "duration": "2:58"
        },
        {
          "number": 6,
          "name": "Mayday (Instrumental)",
          "duration": "3:18"
        },
        {
          "number": 7,
          "name": "Amphisbaena (Instrumental)",
          "duration": "3:04"
        },
        {
          "number": 8,
          "name": "No One's Above (Instrumental)",
          "duration": "3:33"
        }
      ]
    }
  ],
  "singles": [
    {
      "name": "Victim",
      "year": "2025",
      "release_date": "2025-01-31",
      "cover": "https://is1-ssl.mzstatic.com/image/thumb/Music221/v4/e5/00/6a/e5006ad4-686e-2cd3-3640-26d54e787635/cover.jpg/600x600bb.jpg",
      "tracks": [
        {
          "number": 1,
          "name": "Victim",
          "duration": "4:21"
        },
        {
          "number": 2,
          "name": "Purge",
          "duration": "3:13"
        }
      ]
    },
    {
      "name": "Parasite",
      "year": "2022",
      "release_date": "2022-02-11",
      "cover": "https://is1-ssl.mzstatic.com/image/thumb/Music126/v4/9d/ba/90/9dba9012-3e57-c9ed-6a44-7fe9eb9fbf57/196626207432.jpg/600x600bb.jpg",
      "tracks": [
        {
          "number": 1,
          "name": "Parasite",
          "duration": "3:29"
        }
      ]
    },
    {
      "name": "No One's Above",
      "year": "2020",
      "release_date": "2020-10-24",
      "cover": "https://is1-ssl.mzstatic.com/image/thumb/Music124/v4/ce/6b/67/ce6b67a9-f9c7-e882-d24e-e94411615692/artwork.jpg/600x600bb.jpg",
      "tracks": [
        {
          "number": 1,
          "name": "No One's Above",
          "duration": "3:33"
        }
      ]
    },
    {
      "name": "Hell is Other People",
      "year": "2022",
      "release_date": "2022-04-15",
      "cover": "https://is1-ssl.mzstatic.com/image/thumb/Music116/v4/5b/13/ea/5b13eaf7-5a63-3e18-4cf7-ac3253442c47/196626661951.jpg/600x600bb.jpg",
      "tracks": [
        {
          "number": 1,
          "name": "Hell is Other People",
          "duration": "3:39"
        }
      ]
    },
    {
      "name": "Purge",
      "year": "2024",
      "release_date": "2024-12-13",
      "cover": "https://is1-ssl.mzstatic.com/image/thumb/Music211/v4/c6/b7/8a/c6b78a80-c1c3-d68d-7a1b-0d9085526b20/cover.jpg/600x600bb.jpg",
      "tracks": [
        {
          "number": 1,
          "name": "Purge",
          "duration": "3:13"
        }
      ]
    },
    {
      "name": "Mayday",
      "year": "2020",
      "release_date": "2020-09-03",
      "cover": "https://is1-ssl.mzstatic.com/image/thumb/Music114/v4/c1/0c/92/c10c92e1-7a0d-4912-ba01-7dacf7a09cc6/artwork.jpg/600x600bb.jpg",
      "tracks": [
        {
          "number": 1,
          "name": "Mayday",
          "duration": "3:18"
        }
      ]
    },
    {
      "name": "Paralyzed",
      "year": "2022",
      "release_date": "2022-04-07",
      "cover": "https://is1-ssl.mzstatic.com/image/thumb/Music112/v4/ac/d2/63/acd2639a-5c48-beba-0dd0-374093a97612/artwork.jpg/600x600bb.jpg",
      "tracks": [
        {
          "number": 1,
          "name": "Paralyzed",
          "duration": "3:28"
        }
      ]
    },
    {
      "name": "It Ends Tonight",
      "year": "2018",
      "release_date": "2018-07-08",
      "cover": "https://is1-ssl.mzstatic.com/image/thumb/Music113/v4/ee/32/ae/ee32aeb4-a513-29e7-4ad2-8a148a5d11d2/artwork.jpg/600x600bb.jpg",
      "tracks": [
        {
          "number": 1,
          "name": "It Ends Tonight",
          "duration": "3:35"
        }
      ]
    },
    {
      "name": "No One's Below",
      "year": "2021",
      "release_date": "2021-03-23",
      "cover": "https://is1-ssl.mzstatic.com/image/thumb/Music114/v4/78/41/11/78411163-1e09-d38c-40ef-2502633a4b7f/artwork.jpg/600x600bb.jpg",
      "tracks": [
        {
          "number": 1,
          "name": "No One's Below",
          "duration": "2:58"
        }
      ]
    },
    {
      "name": "Illness",
      "year": "2019",
      "release_date": "2019-03-13",
      "cover": "https://is1-ssl.mzstatic.com/image/thumb/Music113/v4/27/99/d4/2799d453-fef9-4ea5-3085-8e1502e1edce/artwork.jpg/600x600bb.jpg",
      "tracks": [
        {
          "number": 1,
          "name": "Illness",
          "duration": "3:21"
        }
      ]
    },
    {
      "name": "Hellbound",
      "year": "2025",
      "release_date": "2025-03-27",
      "cover": "https://is1-ssl.mzstatic.com/image/thumb/Music211/v4/7a/6c/25/7a6c2592-cece-5b79-ec9a-8c5538dc5070/cover.jpg/600x600bb.jpg",
      "tracks": [
        {
          "number": 1,
          "name": "Hellbound",
          "duration": "3:40"
        },
        {
          "number": 2,
          "name": "Victim",
          "duration": "4:21"
        },
        {
          "number": 3,
          "name": "Purge",
          "duration": "3:13"
        }
      ]
    },
    {
      "name": "Amphisbaena",
      "year": "2020",
      "release_date": "2020-07-29",
      "cover": "https://is1-ssl.mzstatic.com/image/thumb/Music114/v4/87/08/0a/87080a30-51cf-d86e-3495-b3b1934b22a7/artwork.jpg/600x600bb.jpg",
      "tracks": [
        {
          "number": 1,
          "name": "Amphisbaena",
          "duration": "3:04"
        }
      ]
    },
    {
      "name": "Beatdown Session, Vol. 1 (feat. Abbie Falls, Silent Generation & 33 Movement)",
      "year": "2023",
      "release_date": "2023-09-01",
      "cover": "https://is1-ssl.mzstatic.com/image/thumb/Music116/v4/6d/d5/92/6dd59205-3fba-39da-1bbc-4004f6307cb3/artwork.jpg/600x600bb.jpg",
      "tracks": [
        {
          "number": 1,
          "name": "Beatdown Session, Vol. 1 (feat. Abbie Falls, Silent Generation & 33 Movement)",
          "duration": "3:50"
        }
      ]
    },
    {
      "name": "Reincarnated Gangsta",
      "year": "2024",
      "release_date": "2024-01-17",
      "cover": "https://is1-ssl.mzstatic.com/image/thumb/Music116/v4/b0/3a/a7/b03aa7c9-33d0-3970-5d31-7e98e810454f/artwork.jpg/600x600bb.jpg",
      "tracks": [
        {
          "number": 1,
          "name": "Reincarnated Gangsta",
          "duration": "2:33"
        }
      ]
    },
    {
      "name": "IMMORTALS (feat. Silent Generation, Abbie Falls, HourHouse & No Face No Case)",
      "year": "2023",
      "release_date": "2023-04-20",
      "cover": "https://is1-ssl.mzstatic.com/image/thumb/Music116/v4/12/9c/b4/129cb462-742f-ea73-fcb6-00541884bf3b/artwork.jpg/600x600bb.jpg",
      "tracks": [
        {
          "number": 1,
          "name": "IMMORTALS (feat. Silent Generation, Abbie Falls, HourHouse & No Face No Case)",
          "duration": "3:58"
        }
      ]
    },
    {
      "name": "Ignorance Is Fear (feat. Abbie Falls & Defocus)",
      "year": "2023",
      "release_date": "2023-06-01",
      "cover": "https://is1-ssl.mzstatic.com/image/thumb/Music126/v4/2d/b7/06/2db706ec-8d57-7501-b883-674e72b7d03d/cover.jpg/600x600bb.jpg",
      "tracks": [
        {
          "number": 1,
          "name": "Ignorance Is Fear (feat. Abbie Falls & Defocus)",
          "duration": "3:01"
        }
      ]
    },
    {
      "name": "Mayday (Live At Knotfest: Pulse of the Maggots) [Live At Knotfest: Pulse of the Maggots]",
      "year": "2021",
      "release_date": "2021-09-09",
      "cover": "https://is1-ssl.mzstatic.com/image/thumb/Music125/v4/f1/af/fd/f1affd8b-1d97-42d7-33ef-8462450d90ed/artwork.jpg/600x600bb.jpg",
      "tracks": [
        {
          "number": 1,
          "name": "Mayday (Live At Knotfest: Pulse Of The Maggots)",
          "duration": "3:17"
        }
      ]
    }
  ],
  "eps": [
    {
      "name": "Hell is Other People",
      "year": "2022",
      "release_date": "2022-11-11",
      "cover": "https://is1-ssl.mzstatic.com/image/thumb/Music122/v4/0b/36/97/0b36971e-0971-8e7a-ad19-d07df718584b/197187068968.jpg/600x600bb.jpg",
      "tracks": [
        {
          "number": 1,
          "name": "Death Row",
          "duration": "3:44"
        },
        {
          "number": 2,
          "name": "Hell is Other People",
          "duration": "3:39"
        },
        {
          "number": 3,
          "name": "Pitch Black",
          "duration": "3:42"
        },
        {
          "number": 4,
          "name": "Parasite",
          "duration": "3:29"
        },
        {
          "number": 5,
          "name": "Absolution",
          "duration": "4:03"
        }
      ]
    },
    {
      "name": "Black Void",
      "year": "2025",
      "release_date": "2025-07-24",
      "cover": "https://is1-ssl.mzstatic.com/image/thumb/Music221/v4/54/ee/d1/54eed1c9-f426-79f8-a7ca-0615bc06df81/cover.jpg/600x600bb.jpg",
      "tracks": [
        {
          "number": 1,
          "name": "Black Void",
          "duration": "3:38"
        },
        {
          "number": 2,
          "name": "Hellbound",
          "duration": "3:40"
        },
        {
          "number": 3,
          "name": "Victim",
          "duration": "4:21"
        },
        {
          "number": 4,
          "name": "Purge",
          "duration": "3:13"
        }
      ]
    },
    {
      "name": "unnatural order",
      "year": "2025",
      "release_date": "2025-09-05",
      "cover": "https://is1-ssl.mzstatic.com/image/thumb/Music211/v4/2c/6e/4c/2c6e4cec-4094-d2ce-a125-eb45dd646689/cover.jpg/600x600bb.jpg",
      "tracks": [
        {
          "number": 1,
          "name": "unnatural order",
          "duration": "3:31"
        },
        {
          "number": 2,
          "name": "Black Void",
          "duration": "3:38"
        },
        {
          "number": 3,
          "name": "Hellbound",
          "duration": "3:40"
        },
        {
          "number": 4,
          "name": "Victim",
          "duration": "4:21"
        },
        {
          "number": 5,
          "name": "Purge",
          "duration": "3:13"
        }
      ]
    }
  ]
}