{
  "name": "acronym.",
  "id": 1677437575,
  "albums": [
    {
      "name": "LUNATIK!",
      "year": "2024",
      "release_date": "2024-03-22",
      "cover": "https://is1-ssl.mzstatic.com/image/thumb/Music211/v4/8d/d8/bf/8dd8bfe0-3042-001e-a803-3837f88de982/cover.jpg/600x600bb.jpg",
      "tracks": [
        {
          "number": 1,
          "name": "LUNATIK!",
          "duration": "1:14"
        }
      ]
    }
  ],
  "singles": [
    {
      "name": "MTG GNOMES BRAZIL",
      "year": "2024",
      "release_date": "2024-07-08",
      "cover": "https://is1-ssl.mzstatic.com/image/thumb/Music211/v4/7b/68/1d/7b681d78-3516-8553-7615-b4e06c61de03/cover.jpg/600x600bb.jpg",
      "tracks": [
        {
          "number": 1,
          "name": "MTG GNOMES BRAZIL",
          "duration": "1:38"
        }
      ]
    },
    {
      "name": "Dark Inside",
      "year": "2023",
      "release_date": "2023-08-18",
      "cover": "https://is1-ssl.mzstatic.com/image/thumb/Music116/v4/6f/fe/4e/6ffe4eda-5d25-3dfa-8896-c01ee882a63f/1963621537654_cover.jpg/600x600bb.jpg",
      "tracks": [
        {
          "number": 1,
          "name": "Dark Inside",
          "duration": "1:51"
        }
      ]
    },
    {
      "name": "TOMA TOMA - slowed + reverb (feat. velocity)",
      "year": "2023",
      "release_date": "2023-05-01",
      "cover": "https://is1-ssl.mzstatic.com/image/thumb/Music126/v4/9c/41/75/9c417592-6f75-b813-fd4a-2143e0481582/1963621338268_cover.jpg/600x600bb.jpg",
      "tracks": [
        {
          "number": 1,
          "name": "TOMA TOMA - slowed + reverb (feat. velocity)",
          "duration": "2:43"
        }
      ]
    },
    {
      "name": "You Don't Have To Call",
      "year": "2023",
      "release_date": "2023-05-05",
      "cover": "https://is1-ssl.mzstatic.com/image/thumb/Music126/v4/84/d1/0c/84d10c28-5258-2793-3065-0b017aa4433e/1963621304386_cover.jpg/600x600bb.jpg",
      "tracks": [
        {
          "number": 1,
          "name": "You Don't Have To Call",
          "duration": "1:59"
        },
        {
          "number": 2,
          "name": "You Don't Have To Call - Sped Up",
          "duration": "1:43"
        },
        {
          "number": 3,
          "name": "You Don't Have To Call - Slowed + Reverb",
          "duration": "2:09"
        }
      ]
    },
    {
      "name": "VI$Ion$",
      "year": "2024",
      "release_date": "2024-02-21",
      "cover": "https://is1-ssl.mzstatic.com/image/thumb/Music116/v4/49/10/3c/49103cbe-1208-96eb-598e-6cefc96c83d6/1963621941888_cover.jpg/600x600bb.jpg",
      "tracks": [
        {
          "number": 1,
          "name": "VI$Ion$",
          "duration": "1:27"
        }
      ]
    },
    {
      "name": "Gray - Slowed",
      "year": "2023",
      "release_date": "2023-09-08",
      "cover": "https://is1-ssl.mzstatic.com/image/thumb/Music116/v4/52/e0/6b/52e06bd7-db9b-66db-2649-d50ba5344eed/1963621593919_cover.jpg/600x600bb.jpg",
      "tracks": [
        {
          "number": 1,
          "name": "Gray - Slowed",
          "duration": "2:33"
        }
      ]
    },
    {
      "name": "Glitched",
      "year": "2024",
      "release_date": "2024-03-22",
      "cover": "https://is1-ssl.mzstatic.com/image/thumb/Music211/v4/85/d3/55/85d3558f-d680-aed2-75a3-93459a1a54f2/1963622029745_cover.jpg/600x600bb.jpg",
      "tracks": [
        {
          "number": 1,
          "name": "Glitched",
          "duration": "1:29"
        }
      ]
    },
    {
      "name": "Toma Toma",
      "year": "2023",
      "release_date": "2023-05-01",
      "cover": "https://is1-ssl.mzstatic.com/image/thumb/Music116/v4/4b/e0/16/4be01607-4591-3102-5522-dd488cb8a966/1963621338251_cover.jpg/600x600bb.jpg",
      "tracks": [
        {
          "number": 1,
          "name": "Toma Toma",
          "duration": "2:27"
        }
      ]
    },
    {
      "name": "Awa Awa Uwu Owo",
      "year": "2023",
      "release_date": "2023-11-24",
      "cover": "https://is1-ssl.mzstatic.com/image/thumb/Music126/v4/97/f8/45/97f8457a-dc49-a644-51f8-3dc701acbc3f/1963621768201_cover.jpg/600x600bb.jpg",
      "tracks": [
        {
          "number": 1,
          "name": "Awa Awa Uwu Owo",
          "duration": "1:16"
        }
      ]
    },
    {
      "name": "Together",
      "year": "2022",
      "release_date": "2022-12-05",
      "cover": "https://is1-ssl.mzstatic.com/image/thumb/Music122/v4/bd/55/98/bd559868-a4bb-b4d2-7f82-9f6a6680f6a3/1963621068516_cover.jpg/600x600bb.jpg",
      "tracks": [
        {
          "number": 1,
          "name": "Coldest Night, Without You",
          "duration": "2:00"
        },
        {
          "number": 2,
          "name": "I'm Into You Babe",
          "duration": "1:56"
        },
        {
          "number": 3,
          "name": "Never Let You Go",
          "duration": "2:02"
        }
      ]
    },
    {
      "name": "Think (Extended)",
      "year": "2023",
      "release_date": "2023-04-13",
      "cover": "https://is1-ssl.mzstatic.com/image/thumb/Music126/v4/dd/f6/18/ddf618b3-d2eb-bf9e-859d-8d5186cf0a4a/1963621270681_cover.jpg/600x600bb.jpg",
      "tracks": [
        {
          "number": 1,
          "name": "Think",
          "duration": "3:59"
        },
        {
          "number": 2,
          "name": "Think - Slowed",
          "duration": "4:25"
        },
        {
          "number": 3,
          "name": "Think - Sped Up",
          "duration": "3:27"
        }
      ]
    },
    {
      "name": "Raining Outside",
      "year": "2023",
      "release_date": "2023-04-06",
      "cover": "https://is1-ssl.mzstatic.com/image/thumb/Music116/v4/fb/de/22/fbde229b-434e-df4f-c6cf-ffc9341e243f/1963621225063_cover.jpg/600x600bb.jpg",
      "tracks": [
        {
          "number": 1,
          "name": "Raining Outside",
          "duration": "1:59"
        }
      ]
    },
    {
      "name": "Treinamento De Testosterona",
      "year": "2023",
      "release_date": "2023-11-10",
      "cover": "https://is1-ssl.mzstatic.com/image/thumb/Music116/v4/38/2f/b3/382fb383-f2a8-bb0b-234f-82f0c41b7944/198092402304_cover.jpg/600x600bb.jpg",
      "tracks": [
        {
          "number": 1,
          "name": "Treinamento De Testosterona",
          "duration": "1:14"
        }
      ]
    },
    {
      "name": "IM Fine",
      "year": "2023",
      "release_date": "2023-02-23",
      "cover": "https://is1-ssl.mzstatic.com/image/thumb/Music126/v4/a1/4c/6c/a14c6cca-9363-cfe2-e57e-5cfcb4a72646/1963621183516_cover.jpg/600x600bb.jpg",
      "tracks": [
        {
          "number": 1,
          "name": "IM Fine",
          "duration": "1:49"
        }
      ]
    },
    {
      "name": "Lost Cause!",
      "year": "2024",
      "release_date": "2024-03-29",
      "cover": "https://is1-ssl.mzstatic.com/image/thumb/Music221/v4/48/5c/58/485c5837-b0c4-46ad-3546-4396caef49fe/1963622029738_cover.jpg/600x600bb.jpg",
      "tracks": [
        {
          "number": 1,
          "name": "Lost Cause!",
          "duration": "2:14"
        }
      ]
    },
    {
      "name": "Bitkrushed",
      "year": "2024",
      "release_date": "2024-02-09",
      "cover": "https://is1-ssl.mzstatic.com/image/thumb/Music221/v4/db/23/6c/db236cde-10d6-b0c0-55e0-96014f892a94/1963621926045_cover.jpg/600x600bb.jpg",
      "tracks": [
        {
          "number": 1,
          "name": "Bitkrushed",
          "duration": "1:33"
        }
      ]
    },
    {
      "name": "DOOF DOOF! - sped up (feat. velocity)",
      "year": "2023",
      "release_date": "2023-03-31",
      "cover": "https://is1-ssl.mzstatic.com/image/thumb/Music126/v4/70/57/a8/7057a811-e8f2-496b-84f5-3356fcef5d46/1963621279943_cover.jpg/600x600bb.jpg",
      "tracks": [
        {
          "number": 1,
          "name": "DOOF DOOF! - sped up (feat. velocity)",
          "duration": "1:19"
        }
      ]
    },
    {
      "name": "Sneaky!",
      "year": "2024",
      "release_date": "2024-06-14",
      "cover": "https://is1-ssl.mzstatic.com/image/thumb/Music221/v4/69/38/27/6938279b-9c37-26f4-af35-89c5889d2e56/1963622217340_cover.jpg/600x600bb.jpg",
      "tracks": [
        {
          "number": 1,
          "name": "Sneaky!",
          "duration": "1:11"
        }
      ]
    },
    {
      "name": "Stay",
      "year": "2023",
      "release_date": "2023-09-15",
      "cover": "https://is1-ssl.mzstatic.com/image/thumb/Music126/v4/ca/9a/cd/ca9acdb3-f10f-88f7-6797-9e2e7bc1e2b9/1963621615055_cover.jpg/600x600bb.jpg",
      "tracks": [
        {
          "number": 1,
          "name": "Stay",
          "duration": "1:49"
        }
      ]
    },
    {
      "name": "Forever",
      "year": "2023",
      "release_date": "2023-08-25",
      "cover": "https://is1-ssl.mzstatic.com/image/thumb/Music126/v4/83/5d/7e/835d7edd-957e-2ae9-9dd5-e4231cd73c8a/1963621496470_cover.jpg/600x600bb.jpg",
      "tracks": [
        {
          "number": 1,
          "name": "Forever",
          "duration": "2:25"
        }
      ]
    },
    {
      "name": "Beautiful Moon",
      "year": "2023",
      "release_date": "2023-07-28",
      "cover": "https://is1-ssl.mzstatic.com/image/thumb/Music116/v4/95/f0/a7/95f0a789-5fa3-689c-bd1e-2737f65851e9/1963621417543_cover.jpg/600x600bb.jpg",
      "tracks": [
        {
          "number": 1,
          "name": "Beautiful Moon",
          "duration": "1:47"
        }
      ]
    },
    {
      "name": "Old Money - Lofi Cover",
      "year": "2023",
      "release_date": "2023-06-08",
      "cover": "https://is1-ssl.mzstatic.com/image/thumb/Music126/v4/05/78/4b/05784b28-d964-1501-4434-efd04dd8c0d7/1963621387778_cover.jpg/600x600bb.jpg",
      "tracks": [
        {
          "number": 1,
          "name": "Old Money - Lofi Cover",
          "duration": "1:52"
        }
      ]
    },
    {
      "name": "Diablo",
      "year": "2023",
      "release_date": "2023-06-22",
      "cover": "https://is1-ssl.mzstatic.com/image/thumb/Music116/v4/3d/75/62/3d75621b-d935-13e0-4515-108658bb6e2c/1963621440060_cover.jpg/600x600bb.jpg",
      "tracks": [
        {
          "number": 1,
          "name": "Diablo",
          "duration": "1:12"
        },
        {
          "number": 2,
          "name": "DIABLO - sped up",
          "duration": "1:05"
        },
        {
          "number": 3,
          "name": "DIABLO - slowed",
          "duration": "1:29"
        }
      ]
    },
    {
      "name": "Not For Me - Slowed + Reverb",
      "year": "2023",
      "release_date": "2023-03-15",
      "cover": "https://is1-ssl.mzstatic.com/image/thumb/Music126/v4/1c/a8/77/1ca8770b-0352-b9d7-b086-887167739801/1963621248956_cover.jpg/600x600bb.jpg",
      "tracks": [
        {
          "number": 1,
          "name": "Not For Me - Slowed + Reverb",
          "duration": "1:50"
        }
      ]
    },
    {
      "name": "Atelier",
      "year": "2023",
      "release_date": "2023-04-06",
      "cover": "https://is1-ssl.mzstatic.com/image/thumb/Music126/v4/b8/4c/b0/b84cb043-a34a-bab1-7c8e-66f5d2668403/cover_4099885450853.jpg/600x600bb.jpg",
      "tracks": [
        {
          "number": 1,
          "name": "Atelier",
          "duration": "2:09"
        }
      ]
    },
    {
      "name": "Wayfaring",
      "year": "2023",
      "release_date": "2023-05-04",
      "cover": "https://is1-ssl.mzstatic.com/image/thumb/Music126/v4/55/15/a7/5515a7ba-9093-e414-f0ae-6628c071240a/cover_4099885486869.jpg/600x600bb.jpg",
      "tracks": [
        {
          "number": 1,
          "name": "Wayfaring",
          "duration": "1:36"
        }
      ]
    },
    {
      "name": "Emperor",
      "year": "2023",
      "release_date": "2023-01-26",
      "cover": "https://is1-ssl.mzstatic.com/image/thumb/Music123/v4/d8/d4/c8/d8d4c85d-451a-7954-e032-ce5e51fadbe4/1963621119461_cover.jpg/600x600bb.jpg",
      "tracks": [
        {
          "number": 1,
          "name": "Emperor",
          "duration": "2:10"
        }
      ]
    },
    {
      "name": "Have You Ever Loved Somebody So Much",
      "year": "2023",
      "release_date": "2023-02-23",
      "cover": "https://is1-ssl.mzstatic.com/image/thumb/Music116/v4/04/80/79/04807925-f743-f066-1e9a-d0609b1b0cf3/1963621168643_cover.jpg/600x600bb.jpg",
      "tracks": [
        {
          "number": 1,
          "name": "Have You Ever Loved Somebody So Much",
          "duration": "1:56"
        }
      ]
    },
    {
      "name": "MISS YOU",
      "year": "2024",
      "release_date": "2024-04-19",
      "cover": "https://is1-ssl.mzstatic.com/image/thumb/Music221/v4/ec/70/8b/ec708b7f-fbc5-f471-80b5-36b120592f68/1963622113802_cover.jpg/600x600bb.jpg",
      "tracks": [
        {
          "number": 1,
          "name": "MISS YOU",
          "duration": "1:50"
        }
      ]
    },
    {
      "name": "Interplay",
      "year": "2023",
      "release_date": "2023-05-05",
      "cover": "https://is1-ssl.mzstatic.com/image/thumb/Music116/v4/63/c8/9a/63c89ab7-81c3-2729-0638-7758333dcb82/1963621304379_cover.jpg/600x600bb.jpg",
      "tracks": [
        {
          "number": 1,
          "name": "Interplay",
          "duration": "2:04"
        },
        {
          "number": 2,
          "name": "Interplay - Sped Up",
          "duration": "1:42"
        },
        {
          "number": 3,
          "name": "Interplay - Slowed + Reverb",
          "duration": "2:24"
        }
      ]
    },
    {
      "name": "Flower Fields",
      "year": "2023",
      "release_date": "2023-11-03",
      "cover": "https://is1-ssl.mzstatic.com/image/thumb/Music126/v4/ea/06/4e/ea064e7e-ccaf-e98a-4132-c6dab6feabdb/1963621682170_cover.jpg/600x600bb.jpg",
      "tracks": [
        {
          "number": 1,
          "name": "Flower Fields",
          "duration": "1:52"
        }
      ]
    },
    {
      "name": "DXD",
      "year": "2024",
      "release_date": "2024-03-08",
      "cover": "https://is1-ssl.mzstatic.com/image/thumb/Music122/v4/3d/d0/52/3dd05221-3baf-345e-d9fe-9fe93e416f71/1963621987985_cover.jpg/600x600bb.jpg",
      "tracks": [
        {
          "number": 1,
          "name": "DXD",
          "duration": "1:26"
        },
        {
          "number": 2,
          "name": "DXD - Slowed",
          "duration": "1:38"
        },
        {
          "number": 3,
          "name": "DXD - Sped Up",
          "duration": "1:17"
        }
      ]
    },
    {
      "name": "Xonar",
      "year": "2024",
      "release_date": "2024-07-26",
      "cover": "https://is1-ssl.mzstatic.com/image/thumb/Music221/v4/a0/79/ae/a079aeff-d055-4954-3ae9-91302110a70a/1963622384967_cover.jpg/600x600bb.jpg",
      "tracks": [
        {
          "number": 1,
          "name": "Xonar",
          "duration": "1:26"
        },
        {
          "number": 2,
          "name": "XONAR - Slowed",
          "duration": "1:44"
        },
        {
          "number": 3,
          "name": "XONAR - Super Slowed",
          "duration": "2:02"
        }
      ]
    },
    {
      "name": "CIMA DO TOMA",
      "year": "2024",
      "release_date": "2024-08-23",
      "cover": "https://is1-ssl.mzstatic.com/image/thumb/Music211/v4/ef/9b/12/ef9b127e-9728-a1a7-ab9d-66235aba8516/1963622368219_cover.jpg/600x600bb.jpg",
      "tracks": [
        {
          "number": 1,
          "name": "CIMA DO TOMA",
          "duration": "1:48"
        },
        {
          "number": 2,
          "name": "CIMA DO TOMA - Slowed",
          "duration": "2:07"
        },
        {
          "number": 3,
          "name": "CIMA DO TOMA - Sped Up",
          "duration": "1:41"
        }
      ]
    },
    {
      "name": "Krushbash",
      "year": "2024",
      "release_date": "2024-02-23",
      "cover": "https://is1-ssl.mzstatic.com/image/thumb/Music112/v4/6e/55/48/6e55483e-63d6-ab9d-9b06-1b8d55e3d186/1963621973896_cover.jpg/600x600bb.jpg",
      "tracks": [
        {
          "number": 1,
          "name": "Krushbash",
          "duration": "1:55"
        },
        {
          "number": 2,
          "name": "KRUSHBASH - slowed",
          "duration": "2:04"
        },
        {
          "number": 3,
          "name": "KRUSHBASH - sped up",
          "duration": "1:35"
        }
      ]
    },
    {
      "name": "Mesa Mesa",
      "year": "2023",
      "release_date": "2023-05-05",
      "cover": "https://is1-ssl.mzstatic.com/image/thumb/Music116/v4/5a/5a/39/5a5a3925-0024-0f1e-1d43-d306c30ba3b7/1963621340704_cover.jpg/600x600bb.jpg",
      "tracks": [
        {
          "number": 1,
          "name": "Mesa Mesa",
          "duration": "1:33"
        }
      ]
    },
    {
      "name": "Hasankrush!",
      "year": "2024",
      "release_date": "2024-02-19",
      "cover": "https://is1-ssl.mzstatic.com/image/thumb/Music126/v4/4e/31/ee/4e31ee18-e94e-8b89-8c4a-cf80710cdc3d/1963621959142_cover.jpg/600x600bb.jpg",
      "tracks": [
        {
          "number": 1,
          "name": "Hasankrush!",
          "duration": "1:13"
        }
      ]
    },
    {
      "name": "TOMA TOMA - super slowed (feat. velocity)",
      "year": "2023",
      "release_date": "2023-05-01",
      "cover": "https://is1-ssl.mzstatic.com/image/thumb/Music126/v4/a2/c1/8c/a2c18c5e-2a99-6ea4-ef9e-379c2bc3cc7e/1963621338282_cover.jpg/600x600bb.jpg",
      "tracks": [
        {
          "number": 1,
          "name": "TOMA TOMA - super slowed (feat. velocity)",
          "duration": "3:12"
        }
      ]
    },
    {
      "name": "DOOF DOOF! - slowed + reverb (feat. velocity)",
      "year": "2023",
      "release_date": "2023-03-31",
      "cover": "https://is1-ssl.mzstatic.com/image/thumb/Music116/v4/6b/f2/d9/6bf2d9a5-83a9-e23f-cde5-e8152d56fada/1963621279936_cover.jpg/600x600bb.jpg",
      "tracks": [
        {
          "number": 1,
          "name": "DOOF DOOF! - slowed + reverb (feat. velocity)",
          "duration": "1:38"
        }
      ]
    },
    {
      "name": "Get You Off My Mind",
      "year": "2023",
      "release_date": "2023-05-05",
      "cover": "https://is1-ssl.mzstatic.com/image/thumb/Music126/v4/a3/0f/b6/a30fb698-c76a-0587-2b8e-dd8c2776af5b/1963621304409_cover.jpg/600x600bb.jpg",
      "tracks": [
        {
          "number": 1,
          "name": "Get You Off My Mind",
          "duration": "2:07"
        },
        {
          "number": 2,
          "name": "Get You Off My Mind - Slowed + Reverb",
          "duration": "2:21"
        }
      ]
    },
    {
      "name": "Krush Me",
      "year": "2024",
      "release_date": "2024-01-24",
      "cover": "https://is1-ssl.mzstatic.com/image/thumb/Music116/v4/3a/d8/d4/3ad8d430-f3f5-c733-ba27-5e2f151379e0/1963621909321_cover.jpg/600x600bb.jpg",
      "tracks": [
        {
          "number": 1,
          "name": "Krush Me",
          "duration": "1:29"
        },
        {
          "number": 2,
          "name": "Krush Me - Slowed",
          "duration": "1:53"
        },
        {
          "number": 3,
          "name": "Krush Me - Sped Up",
          "duration": "1:17"
        }
      ]
    },
    {
      "name": "Hyperion",
      "year": "2023",
      "release_date": "2023-04-07",
      "cover": "https://is1-ssl.mzstatic.com/image/thumb/Music126/v4/e5/90/71/e590711f-87d8-ffb4-b439-abf398772137/1963621288471_cover.jpg/600x600bb.jpg",
      "tracks": [
        {
          "number": 1,
          "name": "Hyperion",
          "duration": "2:07"
        },
        {
          "number": 2,
          "name": "Change",
          "duration": "2:22"
        },
        {
          "number": 3,
          "name": "Purpose",
          "duration": "2:11"
        }
      ]
    },
    {
      "name": "Era Demoniaca",
      "year": "2023",
      "release_date": "2023-11-10",
      "cover": "https://is1-ssl.mzstatic.com/image/thumb/Music116/v4/46/2b/3c/462b3c34-8f44-6f5c-8e9d-b62677b6477e/1963621712433_cover.jpg/600x600bb.jpg",
      "tracks": [
        {
          "number": 1,
          "name": "Era Demoniaca",
          "duration": "1:32"
        }
      ]
    },
    {
      "name": "Creative Space",
      "year": "2022",
      "release_date": "2022-12-21",
      "cover": "https://is1-ssl.mzstatic.com/image/thumb/Music112/v4/25/aa/63/25aa63ab-6e73-bc07-3c35-20245977b98e/1963621053840_cover.jpg/600x600bb.jpg",
      "tracks": [
        {
          "number": 1,
          "name": "Creative Space",
          "duration": "2:06"
        }
      ]
    },
    {
      "name": "Rebola No Meu Caralho II",
      "year": "2024",
      "release_date": "2024-04-05",
      "cover": "https://is1-ssl.mzstatic.com/image/thumb/Music211/v4/c4/d4/7c/c4d47c7b-782b-c7ca-a71f-50ee7fe60a35/1963622032783_cover.jpg/600x600bb.jpg",
      "tracks": [
        {
          "number": 1,
          "name": "Rebola No Meu Caralho II",
          "duration": "1:39"
        }
      ]
    },
    {
      "name": "Doof Doof!",
      "year": "2023",
      "release_date": "2023-03-31",
      "cover": "https://is1-ssl.mzstatic.com/image/thumb/Music116/v4/23/a3/6e/23a36ef7-a517-9525-6961-eabbf2163f6e/1963621279929_cover.jpg/600x600bb.jpg",
      "tracks": [
        {
          "number": 1,
          "name": "Doof Doof!",
          "duration": "1:28"
        }
      ]
    },
    {
      "name": "Hexo",
      "year": "2024",
      "release_date": "2024-05-31",
      "cover": "https://is1-ssl.mzstatic.com/image/thumb/Music221/v4/66/e5/3b/66e53b77-042f-b093-9c1e-fbb068eceda3/1963622237287_cover.jpg/600x600bb.jpg",
      "tracks": [
        {
          "number": 1,
          "name": "Hexo",
          "duration": "1:24"
        },
        {
          "number": 2,
          "name": "HEXO - Sped Up",
          "duration": "1:34"
        },
        {
          "number": 3,
          "name": "HEXO - Super Slowed",
          "duration": "1:37"
        }
      ]
    },
    {
      "name": "Guts II",
      "year": "2023",
      "release_date": "2023-08-11",
      "cover": "https://is1-ssl.mzstatic.com/image/thumb/Music126/v4/28/8e/cd/288ecd47-234a-831a-be29-d3ccb4aeb63a/1963621537616_cover.jpg/600x600bb.jpg",
      "tracks": [
        {
          "number": 1,
          "name": "Guts II",
          "duration": "2:00"
        }
      ]
    },
    {
      "name": "Krush It Up!",
      "year": "2024",
      "release_date": "2024-02-16",
      "cover": "https://is1-ssl.mzstatic.com/image/thumb/Music126/v4/2b/31/ef/2b31ef1f-0982-f01b-b21c-269715f6eec9/1963621934354_cover.jpg/600x600bb.jpg",
      "tracks": [
        {
          "number": 1,
          "name": "Krush It Up!",
          "duration": "1:18"
        },
        {
          "number": 2,
          "name": "KRUSH IT UP! - sped up",
          "duration": "1:09"
        },
        {
          "number": 3,
          "name": "KRUSH IT UP! - slowed",
          "duration": "1:27"
        }
      ]
    },
    {
      "name": "Get Down!",
      "year": "2024",
      "release_date": "2024-04-12",
      "cover": "https://is1-ssl.mzstatic.com/image/thumb/Music211/v4/8f/3e/99/8f3e990e-1bd4-4db6-ad46-610fce643024/1963622082412_cover.jpg/600x600bb.jpg",
      "tracks": [
        {
          "number": 1,
          "name": "Get Down!",
          "duration": "1:58"
        }
      ]
    },
    {
      "name": "SNOBIETY - slowed",
      "year": "2023",
      "release_date": "2023-05-04",
      "cover": "https://is1-ssl.mzstatic.com/image/thumb/Music116/v4/de/5c/01/de5c01aa-cde3-6590-7073-809daef51e1a/1963621320805_cover.jpg/600x600bb.jpg",
      "tracks": [
        {
          "number": 1,
          "name": "SNOBIETY - slowed",
          "duration": "2:21"
        }
      ]
    },
    {
      "name": "SIGMA BRAZIL",
      "year": "2023",
      "release_date": "2023-07-21",
      "cover": "https://is1-ssl.mzstatic.com/image/thumb/Music126/v4/10/8e/a2/108ea2b7-3c07-cf93-9648-74ce309cc6a1/1963621495695_cover.jpg/600x600bb.jpg",
      "tracks": [
        {
          "number": 1,
          "name": "SIGMA BRAZIL",
          "duration": "2:03"
        }
      ]
    },
    {
      "name": "Cannon",
      "year": "2023",
      "release_date": "2023-12-29",
      "cover": "https://is1-ssl.mzstatic.com/image/thumb/Music126/v4/db/ca/c8/dbcac821-6d78-6f05-594f-a822c92a1d97/1963621852276_cover.jpg/600x600bb.jpg",
      "tracks": [
        {
          "number": 1,
          "name": "Cannon",
          "duration": "1:37"
        }
      ]
    },
    {
      "name": "Vida Perigosa",
      "year": "2023",
      "release_date": "2023-06-30",
      "cover": "https://is1-ssl.mzstatic.com/image/thumb/Music116/v4/5d/ba/50/5dba50b3-fe85-6d36-1b5c-9c57df7b0e18/197773174424_cover.jpg/600x600bb.jpg",
      "tracks": [
        {
          "number": 1,
          "name": "Vida Perigosa",
          "duration": "1:41"
        }
      ]
    },
    {
      "name": "Inferno Funk",
      "year": "2024",
      "release_date": "2024-07-26",
      "cover": "https://is1-ssl.mzstatic.com/image/thumb/Music221/v4/cf/9a/38/cf9a38c6-d054-0ee9-7564-515151a0ce5a/1963622324598_cover.jpg/600x600bb.jpg",
      "tracks": [
        {
          "number": 1,
          "name": "Inferno Funk",
          "duration": "1:07"
        },
        {
          "number": 2,
          "name": "INFERNO FUNK - Super Slowed",
          "duration": "1:35"
        }
      ]
    },
    {
      "name": "Run Away",
      "year": "2023",
      "release_date": "2023-02-18",
      "cover": "https://is1-ssl.mzstatic.com/image/thumb/Music126/v4/4a/8a/0d/4a8a0d14-cfb1-c360-60c3-2a6b3da05170/1963621200602_cover.jpg/600x600bb.jpg",
      "tracks": [
        {
          "number": 1,
          "name": "Run Away",
          "duration": "2:06"
        }
      ]
    },
    {
      "name": "Roses",
      "year": "2024",
      "release_date": "2024-02-26",
      "cover": "https://is1-ssl.mzstatic.com/image/thumb/Music116/v4/a6/37/28/a63728d6-9832-df91-f59a-d124e5f22d7a/1963621959203_cover.jpg/600x600bb.jpg",
      "tracks": [
        {
          "number": 1,
          "name": "Roses",
          "duration": "1:48"
        }
      ]
    },
    {
      "name": "Dominio Do Arena",
      "year": "2024",
      "release_date": "2024-03-15",
      "cover": "https://is1-ssl.mzstatic.com/image/thumb/Music112/v4/f4/35/30/f43530c2-9a93-8fa7-81d1-88cd35e4a1ff/1963621969844_cover.jpg/600x600bb.jpg",
      "tracks": [
        {
          "number": 1,
          "name": "Dominio Do Arena",
          "duration": "1:15"
        }
      ]
    },
    {
      "name": "Loved",
      "year": "2023",
      "release_date": "2023-07-14",
      "cover": "https://is1-ssl.mzstatic.com/image/thumb/Music116/v4/a4/4e/78/a44e78d1-5529-82be-5a38-2aa3ae15e4fb/1963621478360_cover.jpg/600x600bb.jpg",
      "tracks": [
        {
          "number": 1,
          "name": "Loved",
          "duration": "2:54"
        },
        {
          "number": 2,
          "name": "Loved - Slowed",
          "duration": "3:10"
        }
      ]
    },
    {
      "name": "DOOF DOOF! - super slowed (feat. velocity)",
      "year": "2023",
      "release_date": "2023-03-31",
      "cover": "https://is1-ssl.mzstatic.com/image/thumb/Music116/v4/8f/81/ae/8f81ae0d-ddb5-0766-4921-b9b257f1f4cf/1963621279950_cover.jpg/600x600bb.jpg",
      "tracks": [
        {
          "number": 1,
          "name": "DOOF DOOF! - super slowed (feat. velocity)",
          "duration": "1:50"
        }
      ]
    },
    {
      "name": "Guerreiro Do Diabo",
      "year": "2023",
      "release_date": "2023-07-13",
      "cover": "https://is1-ssl.mzstatic.com/image/thumb/Music126/v4/27/1c/c5/271cc5ed-e09a-88b5-6978-a6013b16d270/1963621440190_cover.jpg/600x600bb.jpg",
      "tracks": [
        {
          "number": 1,
          "name": "Guerreiro Do Diabo",
          "duration": "1:28"
        }
      ]
    },
    {
      "name": "Not For Me",
      "year": "2023",
      "release_date": "2023-02-18",
      "cover": "https://is1-ssl.mzstatic.com/image/thumb/Music126/v4/99/b4/df/99b4df14-f36e-a3cf-9307-dc27029a56d5/1963621200824_cover.jpg/600x600bb.jpg",
      "tracks": [
        {
          "number": 1,
          "name": "Not For Me",
          "duration": "2:02"
        }
      ]
    },
    {
      "name": "Fükk Off",
      "year": "2024",
      "release_date": "2024-05-10",
      "cover": "https://is1-ssl.mzstatic.com/image/thumb/Music211/v4/63/fd/9b/63fd9b6a-a1cf-0360-e0d2-cabe19793cf9/1963622147005_cover.jpg/600x600bb.jpg",
      "tracks": [
        {
          "number": 1,
          "name": "Fükk Off",
          "duration": "2:08"
        }
      ]
    },
    {
      "name": "Funk Do Diabo",
      "year": "2023",
      "release_date": "2023-06-23",
      "cover": "https://is1-ssl.mzstatic.com/image/thumb/Music126/v4/cd/bc/47/cdbc47e1-11fa-15f3-a688-c8bdd960ab52/1963621401641_cover.jpg/600x600bb.jpg",
      "tracks": [
        {
          "number": 1,
          "name": "Funk Do Diabo",
          "duration": "1:45"
        },
        {
          "number": 2,
          "name": "FUNK DO DIABO - slowed",
          "duration": "2:05"
        }
      ]
    },
    {
      "name": "Cry",
      "year": "2023",
      "release_date": "2023-07-14",
      "cover": "https://is1-ssl.mzstatic.com/image/thumb/Music126/v4/0e/09/9c/0e099c4b-79c8-ee8f-c82f-1e0ba1a6b0d8/1963621451103_cover.jpg/600x600bb.jpg",
      "tracks": [
        {
          "number": 1,
          "name": "Cry",
          "duration": "2:02"
        },
        {
          "number": 2,
          "name": "Cry - Slowed + Reverb",
          "duration": "2:11"
        }
      ]
    },
    {
      "name": "Storm De Brazil",
      "year": "2023",
      "release_date": "2023-12-08",
      "cover": "https://is1-ssl.mzstatic.com/image/thumb/Music126/v4/69/ca/fd/69cafd14-90f8-0f9e-1ab4-7d746c5bfc54/1963621797683_cover.jpg/600x600bb.jpg",
      "tracks": [
        {
          "number": 1,
          "name": "Storm De Brazil",
          "duration": "1:18"
        },
        {
          "number": 2,
          "name": "STORM DE BRAZIL - slowed",
          "duration": "1:22"
        },
        {
          "number": 3,
          "name": "STORM DE BRAZIL - sped up",
          "duration": "1:13"
        }
      ]
    },
    {
      "name": "Rei Do Favela",
      "year": "2023",
      "release_date": "2023-07-28",
      "cover": "https://is1-ssl.mzstatic.com/image/thumb/Music116/v4/e4/fc/d6/e4fcd62e-63f7-0a00-ba36-f0ddfa41dd4b/1963621496487_cover.jpg/600x600bb.jpg",
      "tracks": [
        {
          "number": 1,
          "name": "Rei Do Favela",
          "duration": "1:53"
        },
        {
          "number": 2,
          "name": "REI DO FAVELA - sped up",
          "duration": "1:42"
        },
        {
          "number": 3,
          "name": "REI DO FAVELA - super slowed",
          "duration": "2:21"
        }
      ]
    },
    {
      "name": "Vibe",
      "year": "2023",
      "release_date": "2023-09-22",
      "cover": "https://is1-ssl.mzstatic.com/image/thumb/Music116/v4/7f/2b/a2/7f2ba249-5342-2676-ee50-9cb264ee12c3/1963621626969_cover.jpg/600x600bb.jpg",
      "tracks": [
        {
          "number": 1,
          "name": "Vibe",
          "duration": "1:54"
        }
      ]
    },
    {
      "name": "Automotivo De Testosterona",
      "year": "2024",
      "release_date": "2024-01-26",
      "cover": "https://is1-ssl.mzstatic.com/image/thumb/Music126/v4/d6/79/25/d679256f-96c5-2247-957a-769910f85094/1963621873127_cover.jpg/600x600bb.jpg",
      "tracks": [
        {
          "number": 1,
          "name": "Automotivo De Testosterona",
          "duration": "1:17"
        },
        {
          "number": 2,
          "name": "AUTOMOTIVO DE TESTOSTERONA - Sped Up",
          "duration": "1:09"
        },
        {
          "number": 3,
          "name": "AUTOMOTIVO DE TESTOSTERONA - Super Slowed",
          "duration": "1:32"
        }
      ]
    },
    {
      "name": "Purple Lament.",
      "year": "2023",
      "release_date": "2023-12-15",
      "cover": "https://is1-ssl.mzstatic.com/image/thumb/Music116/v4/ae/8e/2a/ae8e2a19-c2e9-40cf-c604-ccf915ce188b/1963621826352_cover.jpg/600x600bb.jpg",
      "tracks": [
        {
          "number": 1,
          "name": "Purple Lament.",
          "duration": "1:06"
        }
      ]
    },
    {
      "name": "#Krushonme!",
      "year": "2024",
      "release_date": "2024-03-22",
      "cover": "https://is1-ssl.mzstatic.com/image/thumb/Music122/v4/f5/80/01/f580014d-93a7-2aa1-b1a5-91ea6487e43b/1963621976576_cover.jpg/600x600bb.jpg",
      "tracks": [
        {
          "number": 1,
          "name": "#Krushonme!",
          "duration": "1:26"
        }
      ]
    },
    {
      "name": "Feeling Funk",
      "year": "2024",
      "release_date": "2024-08-09",
      "cover": "https://is1-ssl.mzstatic.com/image/thumb/Music211/v4/2e/8b/c3/2e8bc307-9997-8dc5-0972-56ae625d5cdd/1963622368271_cover.jpg/600x600bb.jpg",
      "tracks": [
        {
          "number": 1,
          "name": "Feeling Funk",
          "duration": "1:24"
        }
      ]
    },
    {
      "name": "Krushcore",
      "year": "2024",
      "release_date": "2024-02-02",
      "cover": "https://is1-ssl.mzstatic.com/image/thumb/Music126/v4/cc/de/7f/ccde7f51-de4f-f22a-4207-10d082776d0c/1963621930738_cover.jpg/600x600bb.jpg",
      "tracks": [
        {
          "number": 1,
          "name": "Krushcore",
          "duration": "1:28"
        }
      ]
    },
    {
      "name": "Krush Test (Edits)",
      "year": "2024",
      "release_date": "2024-06-28",
      "cover": "https://is1-ssl.mzstatic.com/image/thumb/Music221/v4/61/96/51/61965158-a7c8-17d3-5485-471e3983dadd/dfb94998-c4cd-4e9a-8ba5-6cccd42368de.jpg/600x600bb.jpg",
      "tracks": [
        {
          "number": 1,
          "name": "KRUSH TEST (Slowed + Reverb)",
          "duration": "1:57"
        },
        {
          "number": 2,
          "name": "KRUSH TEST (Speed Up)",
          "duration": "1:24"
        }
      ]
    },
    {
      "name": "Run Away - Slowed + Reverb",
      "year": "2023",
      "release_date": "2023-03-15",
      "cover": "https://is1-ssl.mzstatic.com/image/thumb/Music116/v4/61/2d/31/612d31eb-2626-9b76-6336-97ab74af0a57/1963621248949_cover.jpg/600x600bb.jpg",
      "tracks": [
        {
          "number": 1,
          "name": "Run Away - Slowed + Reverb",
          "duration": "2:16"
        }
      ]
    },
    {
      "name": "Guts",
      "year": "2023",
      "release_date": "2023-02-23",
      "cover": "https://is1-ssl.mzstatic.com/image/thumb/Music116/v4/f2/33/8f/f2338f4a-5602-fc6f-910c-9155659c1dbe/1963621172879_cover.jpg/600x600bb.jpg",
      "tracks": [
        {
          "number": 1,
          "name": "Guts",
          "duration": "1:19"
        }
      ]
    },
    {
      "name": "Smalltown Boy (Brazil Funk)",
      "year": "2024",
      "release_date": "2024-07-05",
      "cover": "https://is1-ssl.mzstatic.com/image/thumb/Music221/v4/03/87/47/038747e4-d934-5258-ea6f-23a54e8d714c/1963622318351_cover.jpg/600x600bb.jpg",
      "tracks": []
    },
    {
      "name": "Automotivo Infernal Galaxia",
      "year": "2024",
      "release_date": "2024-01-19",
      "cover": "https://is1-ssl.mzstatic.com/image/thumb/Music126/v4/d3/c7/a6/d3c7a692-14b4-0299-5409-6a0b2579c7a4/1963621885700_cover.jpg/600x600bb.jpg",
      "tracks": [
        {
          "number": 1,
          "name": "Automotivo Infernal Galaxia",
          "duration": "1:09"
        },
        {
          "number": 2,
          "name": "AUTOMOTIVO INFERNAL GALAXIA - Slowed",
          "duration": "1:17"
        },
        {
          "number": 3,
          "name": "AUTOMOTIVO INFERNAL GALAXIA - Sped Up",
          "duration": "1:05"
        }
      ]
    },
    {
      "name": "Promises",
      "year": "2023",
      "release_date": "2023-09-22",
      "cover": "https://is1-ssl.mzstatic.com/image/thumb/Music116/v4/b3/2a/2c/b32a2ca3-bec8-7752-de33-c7d6a91f3046/1963621610234_cover.jpg/600x600bb.jpg",
      "tracks": [
        {
          "number": 1,
          "name": "Promises",
          "duration": "1:36"
        }
      ]
    },
    {
      "name": "Desa Desa",
      "year": "2023",
      "release_date": "2023-05-12",
      "cover": "https://is1-ssl.mzstatic.com/image/thumb/Music126/v4/7f/44/2a/7f442a63-9851-ec3d-9cc2-905bdf128f9a/1963621340728_cover.jpg/600x600bb.jpg",
      "tracks": [
        {
          "number": 1,
          "name": "Desa Desa",
          "duration": "1:31"
        }
      ]
    },
    {
      "name": "I love you",
      "year": "2024",
      "release_date": "2024-05-24",
      "cover": "https://is1-ssl.mzstatic.com/image/thumb/Music211/v4/0b/7e/49/0b7e4922-fce9-70fc-ed73-b51aded30e9f/1963622182358_cover.jpg/600x600bb.jpg",
      "tracks": [
        {
          "number": 1,
          "name": "I love you",
          "duration": "1:13"
        }
      ]
    },
    {
      "name": "Rebola No Meu Caralho",
      "year": "2023",
      "release_date": "2023-09-29",
      "cover": "https://is1-ssl.mzstatic.com/image/thumb/Music116/v4/5e/66/86/5e66864a-e7dc-604e-0695-01ae4a656f09/1963621593902_cover.jpg/600x600bb.jpg",
      "tracks": [
        {
          "number": 1,
          "name": "Rebola No Meu Caralho",
          "duration": "1:23"
        }
      ]
    },
    {
      "name": "MONTAGEM BOTADÃO",
      "year": "2024",
      "release_date": "2024-07-12",
      "cover": "https://is1-ssl.mzstatic.com/image/thumb/Music221/v4/74/a0/9e/74a09efd-b5a4-98b4-b823-33ceb8f1c3cb/14950.jpg/600x600bb.jpg",
      "tracks": [
        {
          "number": 1,
          "name": "MONTAGEM BOTADÃO",
          "duration": "2:00"
        },
        {
          "number": 2,
          "name": "MONTAGEM BOTADÃO (Slowed)",
          "duration": "2:24"
        },
        {
          "number": 3,
          "name": "MONTAGEM BOTADÃO (Speed Up)",
          "duration": "1:46"
        }
      ]
    },
    {
      "name": "Krush Test",
      "year": "2024",
      "release_date": "2024-06-28",
      "cover": "https://is1-ssl.mzstatic.com/image/thumb/Music211/v4/fb/84/76/fb8476bf-8673-a24f-e31a-190328036b50/e85987f6-cbbc-4f45-af56-d12b5a9873c0.jpg/600x600bb.jpg",
      "tracks": [
        {
          "number": 1,
          "name": "Krush Test",
          "duration": "1:36"
        }
      ]
    },
    {
      "name": "Snobiety",
      "year": "2023",
      "release_date": "2023-05-04",
      "cover": "https://is1-ssl.mzstatic.com/image/thumb/Music126/v4/8e/6b/ea/8e6beaa8-1fb2-2c34-1bb1-f1a4be436f99/1963621320782_cover.jpg/600x600bb.jpg",
      "tracks": [
        {
          "number": 1,
          "name": "Snobiety",
          "duration": "2:07"
        }
      ]
    },
    {
      "name": "Spark!",
      "year": "2024",
      "release_date": "2024-04-26",
      "cover": "https://is1-ssl.mzstatic.com/image/thumb/Music211/v4/14/20/3d/14203d63-8ad1-e2ab-58db-f467629f0a23/1963622140334_cover.jpg/600x600bb.jpg",
      "tracks": [
        {
          "number": 1,
          "name": "Spark!",
          "duration": "1:14"
        }
      ]
    },
    {
      "name": "Say You're Okay",
      "year": "2023",
      "release_date": "2023-10-13",
      "cover": "https://is1-ssl.mzstatic.com/image/thumb/Music126/v4/ae/e7/6f/aee76f4d-dcde-b8d9-502a-877250b72904/1963621661182_cover.jpg/600x600bb.jpg",
      "tracks": [
        {
          "number": 1,
          "name": "Say You're Okay",
          "duration": "1:52"
        }
      ]
    },
    {
      "name": "VIDA PERIGOSA (Slowed + Reverb)",
      "year": "2023",
      "release_date": "2023-06-29",
      "cover": "https://is1-ssl.mzstatic.com/image/thumb/Music116/v4/3a/40/c5/3a40c571-be91-ce94-5296-9e7972ea5b1d/197773392088_cover.jpg/600x600bb.jpg",
      "tracks": [
        {
          "number": 1,
          "name": "VIDA PERIGOSA (Slowed + Reverb)",
          "duration": "1:59"
        }
      ]
    },
    {
      "name": "Melodia De Vitoria",
      "year": "2024",
      "release_date": "2024-03-01",
      "cover": "https://is1-ssl.mzstatic.com/image/thumb/Music112/v4/ab/cf/dc/abcfdc8f-344f-075f-238b-7dc64f3a593e/1963621983963_cover.jpg/600x600bb.jpg",
      "tracks": [
        {
          "number": 1,
          "name": "Melodia De Vitoria",
          "duration": "1:29"
        },
        {
          "number": 2,
          "name": "MELODIA DE VITORIA - slowed",
          "duration": "1:40"
        },
        {
          "number": 3,
          "name": "MELODIA DE VITORIA - sped up",
          "duration": "1:19"
        }
      ]
    },
    {
      "name": "Matar!",
      "year": "2023",
      "release_date": "2023-08-18",
      "cover": "https://is1-ssl.mzstatic.com/image/thumb/Music126/v4/44/7d/5b/447d5bdb-0c2a-739e-49c3-108b7769494d/1963621514716_cover.jpg/600x600bb.jpg",
      "tracks": [
        {
          "number": 1,
          "name": "Matar!",
          "duration": "1:16"
        }
      ]
    },
    {
      "name": "Please Come Back - Slowed + Reverb",
      "year": "2023",
      "release_date": "2023-03-15",
      "cover": "https://is1-ssl.mzstatic.com/image/thumb/Music126/v4/0a/07/b2/0a07b239-de36-76ec-7112-205cc3470100/1963621248925_cover.jpg/600x600bb.jpg",
      "tracks": [
        {
          "number": 1,
          "name": "Please Come Back - Slowed + Reverb",
          "duration": "2:02"
        }
      ]
    },
    {
      "name": "Mechi",
      "year": "2024",
      "release_date": "2024-05-03",
      "cover": "https://is1-ssl.mzstatic.com/image/thumb/Music211/v4/cf/3f/42/cf3f4274-e520-bdb2-2dc2-2bed53054d90/1963622140341_cover.jpg/600x600bb.jpg",
      "tracks": [
        {
          "number": 1,
          "name": "Mechi",
          "duration": "1:33"
        },
        {
          "number": 2,
          "name": "MECHI - Slowed",
          "duration": "1:47"
        },
        {
          "number": 3,
          "name": "MECHI - Sped Up",
          "duration": "1:25"
        }
      ]
    },
    {
      "name": "Please Stay",
      "year": "2023",
      "release_date": "2023-04-27",
      "cover": "https://is1-ssl.mzstatic.com/image/thumb/Music126/v4/5b/b1/60/5bb160c7-e89a-a896-292a-ad57022b78ee/1963621304362_cover.jpg/600x600bb.jpg",
      "tracks": [
        {
          "number": 1,
          "name": "Please Stay - Slowed Reverb",
          "duration": "2:10"
        },
        {
          "number": 2,
          "name": "Please Stay",
          "duration": "2:02"
        }
      ]
    }
  ],
  "eps": [
    {
      "name": "X - Prime",
      "year": "2024",
      "release_date": "2024-08-22",
      "cover": "https://is1-ssl.mzstatic.com/image/thumb/Music211/v4/c9/e9/cc/c9e9ccfe-8b39-0595-fb5b-5c7ad8d19ee9/751238746788.png/600x600bb.jpg",
      "tracks": [
        {
          "number": 1,
          "name": "X - Prime",
          "duration": "1:32"
        },
        {
          "number": 2,
          "name": "X - Prime (Slowed)",
          "duration": "1:47"
        },
        {
          "number": 3,
          "name": "X - Prime (Sped Up)",
          "duration": "1:25"
        },
        {
          "number": 4,
          "name": "X - Prime (Ultra Slowed)",
          "duration": "1:54"
        }
      ]
    },
    {
      "name": "EAT IT UP FUNK",
      "year": "2024",
      "release_date": "2024-10-25",
      "cover": "https://is1-ssl.mzstatic.com/image/thumb/Music221/v4/56/f9/80/56f980ab-1e39-c58b-c7d4-19e133fb2c14/1963622657733_cover.png/600x600bb.jpg",
      "tracks": [
        {
          "number": 1,
          "name": "EAT IT UP FUNK",
          "duration": "1:11"
        },
        {
          "number": 2,
          "name": "EAT IT UP FUNK (Slowed)",
          "duration": "1:18"
        },
        {
          "number": 3,
          "name": "EAT IT UP FUNK (Super Slowed)",
          "duration": "1:24"
        },
        {
          "number": 4,
          "name": "EAT IT UP FUNK (Ultra Slowed)",
          "duration": "1:30"
        }
      ]
    },
    {
      "name": "SOMBRAS ETERNAS",
      "year": "2025",
      "release_date": "2025-02-22",
      "cover": "https://is1-ssl.mzstatic.com/image/thumb/Music221/v4/ad/2b/f8/ad2bf847-07ab-0e2b-6182-42c36d331903/10733.jpg/600x600bb.jpg",
      "tracks": [
        {
          "number": 1,
          "name": "SOMBRAS ETERNAS",
          "duration": "1:15"
        },
        {
          "number": 2,
          "name": "SOMBRAS ETERNAS (Slowed)",
          "duration": "1:26"
        },
        {
          "number": 3,
          "name": "SOMBRAS ETERNAS (Super Slowed)",
          "duration": "1:37"
        },
        {
          "number": 4,
          "name": "SOMBRAS ETERNAS (Ultra Slowed)",
          "duration": "1:48"
        },
        {
          "number": 5,
          "name": "SOMBRAS ETERNAS (Sped Up)",
          "duration": "1:10"
        }
      ]
    },
    {
      "name": "MENTAL SLIDE",
      "year": "2024",
      "release_date": "2024-08-30",
      "cover": "https://is1-ssl.mzstatic.com/image/thumb/Music221/v4/cd/7f/5c/cd7f5c1c-3dd0-64f9-3e6d-03ed8925bd1b/1963622466212_cover.jpg/600x600bb.jpg",
      "tracks": [
        {
          "number": 1,
          "name": "MENTAL SLIDE",
          "duration": "1:08"
        },
        {
          "number": 2,
          "name": "MENTAL SLIDE (SLOWED)",
          "duration": "1:17"
        },
        {
          "number": 3,
          "name": "MENTAL SLIDE (SPED UP)",
          "duration": "1:01"
        },
        {
          "number": 4,
          "name": "MENTAL SLIDE (ULTRA SLOWED)",
          "duration": "1:25"
        }
      ]
    },
    {
      "name": "MONTAGEM MORENO",
      "year": "2025",
      "release_date": "2025-08-10",
      "cover": "https://is1-ssl.mzstatic.com/image/thumb/Music221/v4/f0/7f/b8/f07fb8c9-4675-0792-fab9-a9d7777cff92/293881.jpg/600x600bb.jpg",
      "tracks": [
        {
          "number": 1,
          "name": "MONTAGEM MORENO",
          "duration": "1:15"
        },
        {
          "number": 2,
          "name": "MONTAGEM MORENO (Slowed)",
          "duration": "1:17"
        },
        {
          "number": 3,
          "name": "MONTAGEM MORENO (Super Slowed)",
          "duration": "1:22"
        },
        {
          "number": 4,
          "name": "MONTAGEM MORENO (Ultra Slowed)",
          "duration": "1:25"
        },
        {
          "number": 5,
          "name": "MONTAGEM MORENO (Sped Up)",
          "duration": "1:12"
        }
      ]
    },
    {
      "name": "Dia Negocio",
      "year": "2025",
      "release_date": "2025-08-14",
      "cover": "https://is1-ssl.mzstatic.com/image/thumb/Music211/v4/a0/cc/35/a0cc350e-9961-f50a-53f7-901d4c7a5e81/038557697251.png/600x600bb.jpg",
      "tracks": [
        {
          "number": 1,
          "name": "Dia Negocio",
          "duration": "1:17"
        },
        {
          "number": 2,
          "name": "Dia Negocio (Slowed)",
          "duration": "1:20"
        },
        {
          "number": 3,
          "name": "Dia Negocio (Super Slowed)",
          "duration": "1:24"
        },
        {
          "number": 4,
          "name": "Dia Negocio (Ultra Slowed)",
          "duration": "1:27"
        },
        {
          "number": 5,
          "name": "Dia Negocio (Sped Up)",
          "duration": "1:14"
        }
      ]
    },
    {
      "name": "Mi Diamante",
      "year": "2025",
      "release_date": "2025-08-12",
      "cover": "https://is1-ssl.mzstatic.com/image/thumb/Music221/v4/26/d7/eb/26d7eb35-fa6d-6dc7-4024-1050c153096c/038557618195.png/600x600bb.jpg",
      "tracks": [
        {
          "number": 1,
          "name": "Mi Diamante",
          "duration": "1:20"
        },
        {
          "number": 2,
          "name": "Mi Diamante (Slowed)",
          "duration": "1:23"
        },
        {
          "number": 3,
          "name": "Mi Diamante (Super Slowed)",
          "duration": "1:27"
        },
        {
          "number": 4,
          "name": "Mi Diamante (Ultra Slowed)",
          "duration": "1:33"
        },
        {
          "number": 5,
          "name": "Mi Diamante (Sped Up)",
          "duration": "1:17"
        }
      ]
    },
    {
      "name": "Taca Taca",
      "year": "2025",
      "release_date": "2025-02-13",
      "cover": "https://is1-ssl.mzstatic.com/image/thumb/Music211/v4/05/31/81/0531812d-ae4a-6fb7-b404-b2976be54ac3/021865822286.png/600x600bb.jpg",
      "tracks": [
        {
          "number": 1,
          "name": "Taca Taca",
          "duration": "1:38"
        },
        {
          "number": 2,
          "name": "Taca Taca (Slowed)",
          "duration": "1:52"
        },
        {
          "number": 3,
          "name": "Taca Taca (Sped Up)",
          "duration": "1:23"
        },
        {
          "number": 4,
          "name": "Taca Taca (Super Slowed)",
          "duration": "2:12"
        },
        {
          "number": 5,
          "name": "Taca Taca (Ultra Slowed)",
          "duration": "2:30"
        }
      ]
    },
    {
      "name": "TREINAMENTO DE TESTOSTERONA (Remixes)",
      "year": "2024",
      "release_date": "2024-03-01",
      "cover": "https://is1-ssl.mzstatic.com/image/thumb/Music126/v4/b4/66/9f/b4669fa1-e052-c8db-9945-6102c207f897/1963621961077_cover.jpg/600x600bb.jpg",
      "tracks": [
        {
          "number": 1,
          "name": "Treinamento De Testosterona",
          "duration": "1:14"
        },
        {
          "number": 2,
          "name": "TREINAMENTO DE TESTOSTERONA - Slowed",
          "duration": "1:23"
        },
        {
          "number": 3,
          "name": "TREINAMENTO DE TESTOSTERONA - Sped Up",
          "duration": "1:06"
        },
        {
          "number": 4,
          "name": "TREINAMENTO DE TESTOSTERONA - Super Slowed",
          "duration": "1:34"
        }
      ]
    },
    {
      "name": "SLIDE DE APOSTA",
      "year": "2024",
      "release_date": "2024-08-09",
      "cover": "https://is1-ssl.mzstatic.com/image/thumb/Music221/v4/7a/9b/07/7a9b07be-1b7e-a858-a11d-dd7bc9158d84/198588963388.jpg/600x600bb.jpg",
      "tracks": [
        {
          "number": 1,
          "name": "SLIDE DE APOSTA",
          "duration": "1:01"
        },
        {
          "number": 2,
          "name": "SLIDE DE APOSTA (SLOWED)",
          "duration": "1:12"
        },
        {
          "number": 3,
          "name": "SLIDE DE APOSTA (LET'S GO GAMBLING)",
          "duration": "1:26"
        },
        {
          "number": 4,
          "name": "SLIDE DE APOSTA (SPED UP)",
          "duration": "0:56"
        }
      ]
    },
    {
      "name": "Fly Up!",
      "year": "2024",
      "release_date": "2024-06-21",
      "cover": "https://is1-ssl.mzstatic.com/image/thumb/Music221/v4/15/3f/3e/153f3ed3-270b-435c-5090-7f4175d2a79e/1963622234194_cover.jpg/600x600bb.jpg",
      "tracks": [
        {
          "number": 1,
          "name": "Fly Up!",
          "duration": "2:37"
        },
        {
          "number": 2,
          "name": "Fly Up! - Sped Up",
          "duration": "2:15"
        },
        {
          "number": 3,
          "name": "Fly Up - Ultraslowed",
          "duration": "3:19"
        },
        {
          "number": 4,
          "name": "Fly Up! - Slowed & Reverb",
          "duration": "2:48"
        }
      ]
    },
    {
      "name": "BALENCA ICHI",
      "year": "2024",
      "release_date": "2024-08-23",
      "cover": "https://is1-ssl.mzstatic.com/image/thumb/Music211/v4/8d/c9/96/8dc996a2-5718-9ef2-e97b-f9eea5443f8e/198662305905_cover.png/600x600bb.jpg",
      "tracks": [
        {
          "number": 1,
          "name": "BALENCA ICHI",
          "duration": "1:53"
        },
        {
          "number": 2,
          "name": "BALENCA ICHI - Slowed",
          "duration": "2:22"
        },
        {
          "number": 3,
          "name": "BALENCA ICHI - Sped Up",
          "duration": "1:40"
        },
        {
          "number": 4,
          "name": "BALENCA ICHI - Super Slowed",
          "duration": "2:49"
        }
      ]
    },
    {
      "name": "Qué Mirás Bobo Funk",
      "year": "2024",
      "release_date": "2024-11-01",
      "cover": "https://is1-ssl.mzstatic.com/image/thumb/Music211/v4/c9/99/3c/c9993c8c-53df-a6ed-63a7-c4cedb56d958/1963622650987_cover.jpg/600x600bb.jpg",
      "tracks": [
        {
          "number": 1,
          "name": "Qué Mirás Bobo Funk",
          "duration": "1:14"
        },
        {
          "number": 2,
          "name": "Qué Mirás Bobo Funk - Slowed",
          "duration": "1:27"
        },
        {
          "number": 3,
          "name": "Qué Mirás Bobo Funk - Super Slowed",
          "duration": "1:43"
        },
        {
          "number": 4,
          "name": "Qué Mirás Bobo Funk - Sped Up",
          "duration": "1:04"
        }
      ]
    },
    {
      "name": "FREAK (Hardstyle)",
      "year": "2024",
      "release_date": "2024-07-14",
      "cover": "https://is1-ssl.mzstatic.com/image/thumb/Music211/v4/9b/8a/53/9b8a53b1-1a71-af8d-7a20-a9f10de4720b/5063466403360_cover.jpg/600x600bb.jpg",
      "tracks": [
        {
          "number": 1,
          "name": "FREAK (Hardstyle)",
          "duration": "2:19"
        },
        {
          "number": 2,
          "name": "FREAK (Hardstyle) - Ultra Slowed",
          "duration": "3:07"
        },
        {
          "number": 3,
          "name": "FREAK (Hardstyle) - Slowed",
          "duration": "2:36"
        },
        {
          "number": 4,
          "name": "FREAK (Hardstyle) - Sped Up",
          "duration": "2:05"
        }
      ]
    },
    {
      "name": "Apaixonei",
      "year": "2024",
      "release_date": "2024-08-02",
      "cover": "https://is1-ssl.mzstatic.com/image/thumb/Music221/v4/c7/20/88/c720883e-03d6-c5fc-3ef5-c469d196f8dc/1963622397240_cover.jpg/600x600bb.jpg",
      "tracks": [
        {
          "number": 1,
          "name": "Apaixonei",
          "duration": "1:25"
        },
        {
          "number": 2,
          "name": "Apaixonei (Sped Up)",
          "duration": "1:16"
        },
        {
          "number": 3,
          "name": "Apaixonei (Slowed)",
          "duration": "1:37"
        },
        {
          "number": 4,
          "name": "Apaixonei (Super Slowed)",
          "duration": "1:49"
        }
      ]
    },
    {
      "name": "Mingle Game Funk (feat. acronym.)",
      "year": "2025",
      "release_date": "2025-01-10",
      "cover": "https://is1-ssl.mzstatic.com/image/thumb/Music211/v4/f5/c0/f7/f5c0f7ae-f87b-e2ce-b5e5-a37fbf54d6f6/1963622839504_cover.jpg/600x600bb.jpg",
      "tracks": [
        {
          "number": 1,
          "name": "Mingle Game Funk (feat. acronym.)",
          "duration": "1:27"
        },
        {
          "number": 2,
          "name": "Mingle Game Funk - Slowed (feat. acronym.)",
          "duration": "1:36"
        },
        {
          "number": 3,
          "name": "Mingle Game Funk - Ultra Slowed (feat. acronym.)",
          "duration": "1:47"
        },
        {
          "number": 4,
          "name": "Mingle Game Funk - Sped Up (feat. acronym.)",
          "duration": "1:18"
        }
      ]
    },
    {
      "name": "DIA NEGOCIO",
      "year": "2025",
      "release_date": "2025-08-14",
      "cover": "https://is1-ssl.mzstatic.com/image/thumb/Music211/v4/ee/b3/c0/eeb3c029-a206-580b-2a44-547f6fc7ee6a/288069.jpg/600x600bb.jpg",
      "tracks": [
        {
          "number": 1,
          "name": "DIA NEGOCIO",
          "duration": "1:17"
        },
        {
          "number": 2,
          "name": "DIA NEGOCIO (Slowed)",
          "duration": "1:20"
        },
        {
          "number": 3,
          "name": "DIA NEGOCIO (Super Slowed)",
          "duration": "1:24"
        },
        {
          "number": 4,
          "name": "DIA NEGOCIO (Ultra Slowed)",
          "duration": "1:27"
        },
        {
          "number": 5,
          "name": "DIA NEGOCIO (Sped Up)",
          "duration": "1:14"
        }
      ]
    },
    {
      "name": "Montagem Moreno",
      "year": "2025",
      "release_date": "2025-08-10",
      "cover": "https://is1-ssl.mzstatic.com/image/thumb/Music211/v4/e0/8b/ac/e08baced-5ab0-022b-23f1-325534caf8f3/038557617921.png/600x600bb.jpg",
      "tracks": [
        {
          "number": 1,
          "name": "Montagem Moreno",
          "duration": "1:15"
        },
        {
          "number": 2,
          "name": "Montagem Moreno (Slowed)",
          "duration": "1:17"
        },
        {
          "number": 3,
          "name": "Montagem Moreno (Super Slowed)",
          "duration": "1:22"
        },
        {
          "number": 4,
          "name": "Montagem Moreno (Ultra Slowed)",
          "duration": "1:25"
        },
        {
          "number": 5,
          "name": "Montagem Moreno (Sped Up)",
          "duration": "1:12"
        }
      ]
    },
    {
      "name": "SOMBRAS ETERNAS",
      "year": "2025",
      "release_date": "2025-02-22",
      "cover": "https://is1-ssl.mzstatic.com/image/thumb/Music211/v4/1e/07/c6/1e07c6c5-842e-431a-b9cf-8049294c8fdf/1043402.jpg/600x600bb.jpg",
      "tracks": [
        {
          "number": 1,
          "name": "SOMBRAS ETERNAS",
          "duration": "1:15"
        },
        {
          "number": 2,
          "name": "SOMBRAS ETERNAS (Slowed)",
          "duration": "1:26"
        },
        {
          "number": 3,
          "name": "SOMBRAS ETERNAS (Super Slowed)",
          "duration": "1:37"
        },
        {
          "number": 4,
          "name": "SOMBRAS ETERNAS (Ultra Slowed)",
          "duration": "1:48"
        },
        {
          "number": 5,
          "name": "SOMBRAS ETERNAS (Sped Up)",
          "duration": "1:10"
        }
      ]
    },
    {
      "name": "X-DUNE",
      "year": "2024",
      "release_date": "2024-10-11",
      "cover": "https://is1-ssl.mzstatic.com/image/thumb/Music211/v4/40/43/6f/40436f25-338d-22d5-ad1a-6d01ef33c689/1963622587870_cover.png/600x600bb.jpg",
      "tracks": [
        {
          "number": 1,
          "name": "X-DUNE",
          "duration": "1:53"
        },
        {
          "number": 2,
          "name": "X-DUNE - Slowed",
          "duration": "2:22"
        },
        {
          "number": 3,
          "name": "X-DUNE - Sped Up",
          "duration": "1:40"
        },
        {
          "number": 4,
          "name": "X-DUNE - Super Slowed",
          "duration": "2:39"
        }
      ]
    },
    {
      "name": "MI DIAMANTE",
      "year": "2025",
      "release_date": "2025-08-12",
      "cover": "https://is1-ssl.mzstatic.com/image/thumb/Music211/v4/56/b4/72/56b4728d-2bbb-1f53-59db-0fe09f9633c3/299205.jpg/600x600bb.jpg",
      "tracks": [
        {
          "number": 1,
          "name": "MI DIAMANTE",
          "duration": "1:20"
        },
        {
          "number": 2,
          "name": "MI DIAMANTE (Slowed)",
          "duration": "1:23"
        },
        {
          "number": 3,
          "name": "MI DIAMANTE (Super Slowed)",
          "duration": "1:27"
        },
        {
          "number": 4,
          "name": "MI DIAMANTE (Ultra Slowed)",
          "duration": "1:33"
        },
        {
          "number": 5,
          "name": "MI DIAMANTE (Sped Up)",
          "duration": "1:17"
        }
      ]
    },
    {
      "name": "SLIDE DE TEMPESTADE",
      "year": "2024",
      "release_date": "2024-10-25",
      "cover": "https://is1-ssl.mzstatic.com/image/thumb/Music211/v4/09/24/a7/0924a783-fb9f-c477-fde8-e6b4aa8b30c2/1963622651038_cover.png/600x600bb.jpg",
      "tracks": [
        {
          "number": 1,
          "name": "SLIDE DE TEMPESTADE",
          "duration": "1:23"
        },
        {
          "number": 2,
          "name": "SLIDE DE TEMPESTADE - SLOWED",
          "duration": "1:33"
        },
        {
          "number": 3,
          "name": "SLIDE DE TEMPESTADE - SUPER SLOWED",
          "duration": "1:44"
        },
        {
          "number": 4,
          "name": "SLIDE DE TEMPESTADE - SPED UP",
          "duration": "1:14"
        }
      ]
    },
    {
      "name": "JUMPY",
      "year": "2025",
      "release_date": "2025-05-02",
      "cover": "https://is1-ssl.mzstatic.com/image/thumb/Music211/v4/99/10/c7/9910c78d-e10a-e4ba-5cf9-b91bc98ba0b2/10745.jpg/600x600bb.jpg",
      "tracks": [
        {
          "number": 1,
          "name": "JUMPY",
          "duration": "1:09"
        },
        {
          "number": 2,
          "name": "JUMPY (Slowed)",
          "duration": "1:27"
        },
        {
          "number": 3,
          "name": "JUMPY (Ultra Slowed)",
          "duration": "1:38"
        },
        {
          "number": 4,
          "name": "JUMPY (Sped Up)",
          "duration": "1:05"
        }
      ]
    },
    {
      "name": "Ta Nav",
      "year": "2024",
      "release_date": "2024-07-05",
      "cover": "https://is1-ssl.mzstatic.com/image/thumb/Music211/v4/2b/83/00/2b830050-b2a5-d81e-bbf4-afadf5ea457a/1963622318382_cover.jpg/600x600bb.jpg",
      "tracks": [
        {
          "number": 1,
          "name": "Ta Nav",
          "duration": "1:29"
        },
        {
          "number": 2,
          "name": "TA NAV - slowed",
          "duration": "1:46"
        },
        {
          "number": 3,
          "name": "TA NAV - sped up",
          "duration": "1:21"
        },
        {
          "number": 4,
          "name": "TA NAV - super slowed",
          "duration": "1:56"
        }
      ]
    },
    {
      "name": "Cemetery Date (Hardstyle)",
      "year": "2024",
      "release_date": "2024-10-25",
      "cover": "https://is1-ssl.mzstatic.com/image/thumb/Music221/v4/f0/db/b7/f0dbb78e-4cd8-ac92-a009-2b455724eb3b/1963622620782_cover.jpg/600x600bb.jpg",
      "tracks": [
        {
          "number": 1,
          "name": "Cemetery Date (Hardstyle)",
          "duration": "2:19"
        },
        {
          "number": 2,
          "name": "Cemetery Date (Hardstyle) - Ultra Slowed",
          "duration": "3:03"
        },
        {
          "number": 3,
          "name": "Cemetery Date (Hardstyle) - Slowed",
          "duration": "2:37"
        },
        {
          "number": 4,
          "name": "Cemetery Date (Hardstyle) - Sped Up",
          "duration": "2:02"
        }
      ]
    },
    {
      "name": "PAPI FUNK",
      "year": "2024",
      "release_date": "2024-09-06",
      "cover": "https://is1-ssl.mzstatic.com/image/thumb/Music221/v4/e9/cd/8f/e9cd8fc7-fd01-2ad7-9292-a69dbb6c97bc/cover.jpg/600x600bb.jpg",
      "tracks": [
        {
          "number": 1,
          "name": "PAPI FUNK",
          "duration": "1:12"
        },
        {
          "number": 2,
          "name": "PAPI FUNK (Slowed)",
          "duration": "1:22"
        },
        {
          "number": 3,
          "name": "PAPI FUNK (Super Slowed)",
          "duration": "1:33"
        },
        {
          "number": 4,
          "name": "PAPI FUNK (Ultra Slowed)",
          "duration": "1:49"
        },
        {
          "number": 5,
          "name": "PAPI FUNK (Sped Up)",
          "duration": "1:07"
        }
      ]
    },
    {
      "name": "JUMPY",
      "year": "2025",
      "release_date": "2025-05-02",
      "cover": "https://is1-ssl.mzstatic.com/image/thumb/Music211/v4/5d/09/f5/5d09f546-0ac1-d8ee-21f8-9dc14e1f32ee/10745.jpg/600x600bb.jpg",
      "tracks": [
        {
          "number": 1,
          "name": "JUMPY",
          "duration": "1:09"
        },
        {
          "number": 2,
          "name": "JUMPY (Slowed)",
          "duration": "1:27"
        },
        {
          "number": 3,
          "name": "JUMPY (Ultra Slowed)",
          "duration": "1:38"
        },
        {
          "number": 4,
          "name": "JUMPY (Sped Up)",
          "duration": "1:05"
        }
      ]
    }
  ]
}