{
  "name": "Dooz Kawa",
  "id": 402640041,
  "albums": [
    {
      "name": "Nomad's Land",
      "year": "2020",
      "release_date": "2020-01-31",
      "cover": "https://is1-ssl.mzstatic.com/image/thumb/Music123/v4/58/c9/12/58c9124c-3704-2040-d052-7d1a73aff7d6/Cover.jpg/600x600bb.jpg",
      "tracks": [
        {
          "number": 1,
          "name": "Loup des steppes",
          "duration": "3:08"
        },
        {
          "number": 2,
          "name": "Arcueil Cachan (feat. Shantel)",
          "duration": "3:34"
        },
        {
          "number": 3,
          "name": "Plumes",
          "duration": "2:58"
        },
        {
          "number": 4,
          "name": "Passions tristes",
          "duration": "4:19"
        },
        {
          "number": 5,
          "name": "Ode à l'état",
          "duration": "3:43"
        },
        {
          "number": 6,
          "name": "La Résistance",
          "duration": "2:28"
        },
        {
          "number": 7,
          "name": "Chill Morrisson (feat. Davodka et Swift Guad)",
          "duration": "4:36"
        },
        {
          "number": 8,
          "name": "Artiste",
          "duration": "3:41"
        },
        {
          "number": 9,
          "name": "Si ce monde... (feat. Dorian Astor)",
          "duration": "4:38"
        },
        {
          "number": 10,
          "name": "Rap sale",
          "duration": "4:03"
        },
        {
          "number": 11,
          "name": "Sous la pluie (feat. Swift Guad)",
          "duration": "3:47"
        },
        {
          "number": 12,
          "name": "La vague (feat. Gaël Faye et Dorian Astor)",
          "duration": "3:53"
        },
        {
          "number": 13,
          "name": "Milo",
          "duration": "3:05"
        }
      ]
    },
    {
      "name": "Contes Cruels",
      "year": "2017",
      "release_date": "2017-11-10",
      "cover": "https://is1-ssl.mzstatic.com/image/thumb/Music118/v4/57/7a/c2/577ac226-ff98-8ee9-b0e1-143be96fcad8/Cover.jpg/600x600bb.jpg",
      "tracks": [
        {
          "number": 1,
          "name": "La couleur des émotions",
          "duration": "2:05"
        },
        {
          "number": 2,
          "name": "Le monstre",
          "duration": "3:19"
        },
        {
          "number": 3,
          "name": "Intro Astro",
          "duration": "0:52"
        },
        {
          "number": 4,
          "name": "L'astronaute",
          "duration": "2:50"
        },
        {
          "number": 5,
          "name": "Bayou",
          "duration": "2:39"
        },
        {
          "number": 6,
          "name": "Le temps des assassins",
          "duration": "4:57"
        },
        {
          "number": 7,
          "name": "Désobéir",
          "duration": "3:23"
        },
        {
          "number": 8,
          "name": "Mauvaise graine",
          "duration": "3:06"
        },
        {
          "number": 9,
          "name": "Si la misère t'amuse",
          "duration": "3:59"
        },
        {
          "number": 10,
          "name": "Fleurs de cerisiers",
          "duration": "4:32"
        },
        {
          "number": 11,
          "name": "L'oiseau mort",
          "duration": "2:13"
        },
        {
          "number": 12,
          "name": "Les rues de ma vie",
          "duration": "3:10"
        }
      ]
    },
    {
      "name": "Vol de Nuit",
      "year": "2024",
      "release_date": "2024-09-20",
      "cover": "https://is1-ssl.mzstatic.com/image/thumb/Music221/v4/d3/bb/20/d3bb20f7-55df-4b12-ef40-b211fb915b64/Cover.jpg/600x600bb.jpg",
      "tracks": [
        {
          "number": 1,
          "name": "Sans pluie pas d’arc-en-ciel",
          "duration": "4:17"
        },
        {
          "number": 2,
          "name": "La Folia",
          "duration": "4:34"
        },
        {
          "number": 3,
          "name": "Espèce à part",
          "duration": "2:48"
        },
        {
          "number": 4,
          "name": "Animals",
          "duration": "2:44"
        },
        {
          "number": 5,
          "name": "Pièges à loups",
          "duration": "4:21"
        },
        {
          "number": 6,
          "name": "Les monstres (feat. Demi Portion)",
          "duration": "3:01"
        },
        {
          "number": 7,
          "name": "Así es la vida (feat. Euphonik & Swift Guad)",
          "duration": "3:52"
        },
        {
          "number": 8,
          "name": "Naufragés",
          "duration": "6:39"
        },
        {
          "number": 9,
          "name": "L’Éléphant blanc",
          "duration": "3:31"
        },
        {
          "number": 10,
          "name": "Bad Boy",
          "duration": "3:52"
        },
        {
          "number": 11,
          "name": "Interlude Don Quichotte (feat. Saligo)",
          "duration": "2:57"
        },
        {
          "number": 12,
          "name": "Sisyphe",
          "duration": "3:19"
        },
        {
          "number": 13,
          "name": "Explosion de fleurs",
          "duration": "3:55"
        },
        {
          "number": 14,
          "name": "SPQR",
          "duration": "3:41"
        },
        {
          "number": 15,
          "name": "Qui je suis",
          "duration": "3:55"
        }
      ]
    },
    {
      "name": "Bohemian Rap Story",
      "year": "2016",
      "release_date": "2016-05-20",
      "cover": "https://is1-ssl.mzstatic.com/image/thumb/Music128/v4/d2/ba/b6/d2bab6d6-c4eb-9b46-0c58-6b1f019a7ddc/Cover.jpg/600x600bb.jpg",
      "tracks": [
        {
          "number": 1,
          "name": "Me faire la belle",
          "duration": "3:33"
        },
        {
          "number": 2,
          "name": "Soirée noire",
          "duration": "3:39"
        },
        {
          "number": 3,
          "name": "Guillotine (feat. Lucio Bukowski)",
          "duration": "4:19"
        },
        {
          "number": 4,
          "name": "Crépuscule d'apocalypse",
          "duration": "4:57"
        },
        {
          "number": 5,
          "name": "Lagrima (feat. Dahko Nektah)",
          "duration": "4:14"
        },
        {
          "number": 6,
          "name": "Chasseur de rimes",
          "duration": "3:31"
        },
        {
          "number": 7,
          "name": "Brako (feat. Hippocampe Fou)",
          "duration": "4:19"
        },
        {
          "number": 8,
          "name": "Trop jeune pour dormir",
          "duration": "4:11"
        },
        {
          "number": 9,
          "name": "Gel douche au chocolat (feat. Tekilla & Dahko Nektah)",
          "duration": "4:44"
        },
        {
          "number": 10,
          "name": "Si les anges n'ont pas de sexe",
          "duration": "4:16"
        },
        {
          "number": 11,
          "name": "Maison citrouille (feat. Anton Serra)",
          "duration": "4:03"
        },
        {
          "number": 12,
          "name": "Palimpseste",
          "duration": "3:51"
        }
      ]
    },
    {
      "name": "Message aux anges noirs",
      "year": "2012",
      "release_date": "2012-06-15",
      "cover": "https://is1-ssl.mzstatic.com/image/thumb/Music124/v4/6a/d6/d0/6ad6d09c-17f2-b523-8dac-9a12c77ddca7/Cover.jpg/600x600bb.jpg",
      "tracks": [
        {
          "number": 1,
          "name": "Message aux anges noirs",
          "duration": "4:12"
        },
        {
          "number": 2,
          "name": "Brûler les illusions",
          "duration": "4:17"
        },
        {
          "number": 3,
          "name": "Le bétail",
          "duration": "3:33"
        },
        {
          "number": 4,
          "name": "La maison (feat. Zsuzsanna Varkoni)",
          "duration": "3:27"
        },
        {
          "number": 5,
          "name": "Radio rap (feat. Al'tarba)",
          "duration": "3:03"
        },
        {
          "number": 6,
          "name": "Do ré mi",
          "duration": "4:07"
        },
        {
          "number": 7,
          "name": "Haa yaa (feat. DJ Click)",
          "duration": "2:17"
        },
        {
          "number": 8,
          "name": "Story d'une souris triste",
          "duration": "4:19"
        },
        {
          "number": 9,
          "name": "Trois étapes",
          "duration": "4:25"
        },
        {
          "number": 10,
          "name": "Syndicat de la rime",
          "duration": "3:22"
        },
        {
          "number": 11,
          "name": "MC",
          "duration": "4:07"
        },
        {
          "number": 12,
          "name": "Des pommes pourries",
          "duration": "4:50"
        },
        {
          "number": 13,
          "name": "Journaliste",
          "duration": "2:40"
        }
      ]
    },
    {
      "name": "Etoiles du sol",
      "year": "2010",
      "release_date": "2010-06-02",
      "cover": "https://is1-ssl.mzstatic.com/image/thumb/Music114/v4/b7/f6/7b/b7f67b27-771c-e11c-273b-c486c6274a74/Cover.jpg/600x600bb.jpg",
      "tracks": [
        {
          "number": 1,
          "name": "Balalaïka (feat. Mandino Reinhardt)",
          "duration": "3:17"
        },
        {
          "number": 2,
          "name": "Narcozik",
          "duration": "3:43"
        },
        {
          "number": 3,
          "name": "Poupée de son",
          "duration": "3:43"
        },
        {
          "number": 4,
          "name": "Les hommes et les armes",
          "duration": "4:37"
        },
        {
          "number": 5,
          "name": "Etoiles du sol",
          "duration": "3:47"
        },
        {
          "number": 6,
          "name": "Bouquet de proses",
          "duration": "5:01"
        },
        {
          "number": 7,
          "name": "Dieu d'amour",
          "duration": "5:05"
        },
        {
          "number": 8,
          "name": "Parker Charlie",
          "duration": "3:57"
        },
        {
          "number": 9,
          "name": "Rap de branleur",
          "duration": "3:58"
        },
        {
          "number": 10,
          "name": "Un jour d'hiver",
          "duration": "3:28"
        },
        {
          "number": 11,
          "name": "Demi monde",
          "duration": "3:45"
        },
        {
          "number": 12,
          "name": "Cherche l'amour",
          "duration": "4:17"
        },
        {
          "number": 13,
          "name": "Bondie",
          "duration": "4:54"
        }
      ]
    }
  ],
  "singles": [
    {
      "name": "Naufragés",
      "year": "2024",
      "release_date": "2024-06-21",
      "cover": "https://is1-ssl.mzstatic.com/image/thumb/Music221/v4/6f/da/db/6fdadbba-ea19-5ec6-9be9-4ab39907898b/Cover.jpg/600x600bb.jpg",
      "tracks": [
        {
          "number": 1,
          "name": "Naufragés",
          "duration": "6:39"
        }
      ]
    },
    {
      "name": "Passions tristes",
      "year": "2020",
      "release_date": "2020-02-14",
      "cover": "https://is1-ssl.mzstatic.com/image/thumb/Music123/v4/07/d8/59/07d859ab-f087-2fda-aeef-17f7f7de5cc2/Cover.jpg/600x600bb.jpg",
      "tracks": [
        {
          "number": 1,
          "name": "Passions tristes",
          "duration": "4:19"
        }
      ]
    },
    {
      "name": "Urgences musicales (feat. Greenfinch, Swift Guad, Saligo, Dah Conectah, Nano, Dooz Kawa, Davodka, Demi Portion & Degiheugi)",
      "year": "2020",
      "release_date": "2020-04-02",
      "cover": "https://is1-ssl.mzstatic.com/image/thumb/Music123/v4/bc/1f/48/bc1f4877-9f00-d4f3-26be-ab41c510be70/Cover.jpg/600x600bb.jpg",
      "tracks": [
        {
          "number": 1,
          "name": "Urgences musicales (feat. Greenfinch, Swift Guad, Saligo, Dah Conectah, Nano, Dooz Kawa, Davodka, Demi Portion & Degiheugi)",
          "duration": "8:28"
        }
      ]
    },
    {
      "name": "La mémoire des jours (feat. Melan, Tekilla, D.Ace, Zippo, Davodka, Le Bon Nob, Ywill, Oprim, Saknes, Lautrec, Dooz Kawa, Guilty, Frimsa, Fhat-R, Ganjre The Giant & Dj Venum)",
      "year": "2019",
      "release_date": "2019-03-12",
      "cover": "https://is1-ssl.mzstatic.com/image/thumb/Music125/v4/9e/b4/38/9eb438df-5c2e-510f-6350-f31ad6f46f89/3664216014335.png/600x600bb.jpg",
      "tracks": [
        {
          "number": 1,
          "name": "La mémoire des jours (feat. Melan, Tekilla, D.Ace, Zippo, Davodka, Le Bon Nob, Ywill, Oprim, Saknes, Lautrec, Dooz Kawa, Guilty, Frimsa, Fhat-R, Ganjre The Giant & Dj Venum)",
          "duration": "7:49"
        }
      ]
    },
    {
      "name": "Arcueil Cachan (feat. Shantel)",
      "year": "2019",
      "release_date": "2019-12-06",
      "cover": "https://is1-ssl.mzstatic.com/image/thumb/Music113/v4/51/78/8b/51788b4f-410f-6faf-00e3-207744f2a354/Cover.jpg/600x600bb.jpg",
      "tracks": [
        {
          "number": 1,
          "name": "Arcueil Cachan (feat. Shantel)",
          "duration": "3:34"
        }
      ]
    },
    {
      "name": "Persona Non Grata (feat. Ol Zico, Dooz Kawa, Aka Seul Two, Euphonik, Max Paro, Polsko & Grödash)",
      "year": "2021",
      "release_date": "2021-11-19",
      "cover": "https://is1-ssl.mzstatic.com/image/thumb/Music126/v4/dc/52/8d/dc528d12-30ff-8e29-d327-45bb50eec984/3664216037181.png/600x600bb.jpg",
      "tracks": [
        {
          "number": 1,
          "name": "Persona Non Grata (feat. Ol Zico, Dooz Kawa, Aka Seul Two, Euphonik, Max Paro, Polsko & Grödash)",
          "duration": "4:43"
        }
      ]
    },
    {
      "name": "Sous la pluie (feat. Swift Guad)",
      "year": "2020",
      "release_date": "2020-01-24",
      "cover": "https://is1-ssl.mzstatic.com/image/thumb/Music113/v4/fd/68/7a/fd687aa6-1192-e217-733d-1f2b9059f86c/Cover.jpg/600x600bb.jpg",
      "tracks": [
        {
          "number": 1,
          "name": "Sous la pluie (feat. Swift Guad)",
          "duration": "3:47"
        }
      ]
    },
    {
      "name": "Toxique (feat. Dooz Kawa)",
      "year": "2022",
      "release_date": "2022-09-02",
      "cover": "https://is1-ssl.mzstatic.com/image/thumb/Music112/v4/19/70/3a/19703a82-4aea-91fa-d5ab-ef546b649152/artwork.jpg/600x600bb.jpg",
      "tracks": [
        {
          "number": 1,
          "name": "Toxique (feat. Dooz Kawa)",
          "duration": "3:06"
        }
      ]
    },
    {
      "name": "Strasbourg",
      "year": "2022",
      "release_date": "2022-03-25",
      "cover": "https://is1-ssl.mzstatic.com/image/thumb/Music116/v4/75/5d/94/755d94de-ae4a-1c38-5141-d68aef303a27/Cover.jpg/600x600bb.jpg",
      "tracks": [
        {
          "number": 1,
          "name": "Strasbourg",
          "duration": "3:42"
        }
      ]
    },
    {
      "name": "Les monstres",
      "year": "2024",
      "release_date": "2024-09-06",
      "cover": "https://is1-ssl.mzstatic.com/image/thumb/Music211/v4/91/de/41/91de4151-a514-9dbf-578a-8141d4ecaef7/Cover.jpg/600x600bb.jpg",
      "tracks": [
        {
          "number": 1,
          "name": "Les monstres",
          "duration": "3:01"
        }
      ]
    },
    {
      "name": "Histoire d'eau",
      "year": "2024",
      "release_date": "2024-04-16",
      "cover": "https://is1-ssl.mzstatic.com/image/thumb/Music211/v4/f5/ab/ec/f5abece5-5607-3d24-204a-4209392ead59/Cover.jpg/600x600bb.jpg",
      "tracks": [
        {
          "number": 1,
          "name": "Histoire d'eau",
          "duration": "4:18"
        }
      ]
    },
    {
      "name": "Le temps des assassins",
      "year": "2017",
      "release_date": "2017-09-26",
      "cover": "https://is1-ssl.mzstatic.com/image/thumb/Music118/v4/a8/6a/63/a86a637e-2a53-96b5-2f54-f3e37aa31f71/Cover.jpg/600x600bb.jpg",
      "tracks": [
        {
          "number": 1,
          "name": "Le temps des assassins",
          "duration": "5:02"
        }
      ]
    },
    {
      "name": "Sisyphe",
      "year": "2024",
      "release_date": "2024-09-19",
      "cover": "https://is1-ssl.mzstatic.com/image/thumb/Music211/v4/9e/94/8b/9e948b3a-e2b3-c240-11aa-20b15446999f/Cover.jpg/600x600bb.jpg",
      "tracks": [
        {
          "number": 1,
          "name": "Sisyphe",
          "duration": "3:19"
        }
      ]
    },
    {
      "name": "La Fin des Contes",
      "year": "2022",
      "release_date": "2022-05-05",
      "cover": "https://is1-ssl.mzstatic.com/image/thumb/Music221/v4/b6/0c/ba/b60cbaf2-f788-3c4a-6a51-e8c51ee62b3d/3663729326218_cover.jpg/600x600bb.jpg",
      "tracks": [
        {
          "number": 1,
          "name": "La Fin des Contes",
          "duration": "3:56"
        }
      ]
    }
  ],
  "eps": [
    {
      "name": "Narcozik #3",
      "year": "2024",
      "release_date": "2024-04-12",
      "cover": "https://is1-ssl.mzstatic.com/image/thumb/Music221/v4/55/34/3f/55343f6b-6f34-770b-1c61-ff30e1bad540/Cover.jpg/600x600bb.jpg",
      "tracks": [
        {
          "number": 1,
          "name": "Histoire d'eau",
          "duration": "4:18"
        },
        {
          "number": 2,
          "name": "Juste 30 secondes",
          "duration": "1:38"
        },
        {
          "number": 3,
          "name": "Le Cirque la nuit",
          "duration": "3:32"
        },
        {
          "number": 4,
          "name": "Le Temps perdu",
          "duration": "2:40"
        },
        {
          "number": 5,
          "name": "Sirènes",
          "duration": "3:26"
        }
      ]
    },
    {
      "name": "Narcozik #1",
      "year": "2013",
      "release_date": "2013-12-18",
      "cover": "https://is1-ssl.mzstatic.com/image/thumb/Music114/v4/bd/7d/1f/bd7d1fcb-4245-376d-0366-80e0d1b85ba3/Cover.jpg/600x600bb.jpg",
      "tracks": [
        {
          "number": 1,
          "name": "Utopistes debout!",
          "duration": "2:26"
        },
        {
          "number": 2,
          "name": "Berceuz pour insomniaks",
          "duration": "3:36"
        },
        {
          "number": 3,
          "name": "Le prince noir",
          "duration": "3:30"
        },
        {
          "number": 4,
          "name": "Les oies sauvages",
          "duration": "3:13"
        },
        {
          "number": 5,
          "name": "Mr Tosh",
          "duration": "3:55"
        }
      ]
    },
    {
      "name": "Narcozik #2",
      "year": "2014",
      "release_date": "2014-09-15",
      "cover": "https://is1-ssl.mzstatic.com/image/thumb/Music124/v4/93/31/95/933195b5-b2df-155e-3707-3aeccdbb6be7/Cover.jpg/600x600bb.jpg",
      "tracks": [
        {
          "number": 1,
          "name": "Perce neige",
          "duration": "4:30"
        },
        {
          "number": 2,
          "name": "A l'arrière des bars",
          "duration": "4:12"
        },
        {
          "number": 3,
          "name": "Prenez les escaliers",
          "duration": "3:54"
        },
        {
          "number": 4,
          "name": "Le savoir est une arme",
          "duration": "4:45"
        },
        {
          "number": 5,
          "name": "Dommages collatéraux",
          "duration": "4:46"
        }
      ]
    }
  ]
}