{
  "name": "FANGZ",
  "id": 1496178388,
  "albums": [
    {
      "name": "Shui",
      "year": "2025",
      "release_date": "2025-07-04",
      "cover": "https://is1-ssl.mzstatic.com/image/thumb/Music211/v4/38/b4/68/38b4684d-b4e5-0074-5d37-c8fb09b3b5cb/IMP139.jpg/600x600bb.jpg",
      "tracks": [
        {
          "number": 1,
          "name": "Wide Awake",
          "duration": "2:59"
        },
        {
          "number": 2,
          "name": "Animals",
          "duration": "2:49"
        },
        {
          "number": 3,
          "name": "Anne Marie",
          "duration": "2:41"
        },
        {
          "number": 4,
          "name": "Gone",
          "duration": "3:07"
        },
        {
          "number": 5,
          "name": "Same Old Story",
          "duration": "2:24"
        },
        {
          "number": 6,
          "name": "Wasting Time",
          "duration": "3:04"
        },
        {
          "number": 7,
          "name": "Sinking",
          "duration": "0:34"
        },
        {
          "number": 8,
          "name": "Bad News",
          "duration": "3:14"
        },
        {
          "number": 9,
          "name": "Nothing to Lose",
          "duration": "2:24"
        },
        {
          "number": 10,
          "name": "Something Real",
          "duration": "2:44"
        },
        {
          "number": 11,
          "name": "Expired",
          "duration": "3:17"
        }
      ]
    }
  ],
  "singles": [
    {
      "name": "Falling Out",
      "year": "2020",
      "release_date": "2020-02-07",
      "cover": "https://is1-ssl.mzstatic.com/image/thumb/Music123/v4/d2/23/36/d22336c3-f1df-36be-3325-56e7a4088320/3461.jpg/600x600bb.jpg",
      "tracks": [
        {
          "number": 1,
          "name": "Falling Out",
          "duration": "3:29"
        }
      ]
    },
    {
      "name": "Wide Awake",
      "year": "2024",
      "release_date": "2024-11-28",
      "cover": "https://is1-ssl.mzstatic.com/image/thumb/Music221/v4/3c/09/a1/3c09a18f-10d0-c3a9-e916-0a786496fd17/XEL25468.jpg/600x600bb.jpg",
      "tracks": [
        {
          "number": 1,
          "name": "Wide Awake",
          "duration": "2:59"
        }
      ]
    },
    {
      "name": "Won't Be Me",
      "year": "2021",
      "release_date": "2021-11-12",
      "cover": "https://is1-ssl.mzstatic.com/image/thumb/Music115/v4/4f/47/26/4f47266e-3ec9-99a2-3ba8-e61f5b83e131/23867.jpg/600x600bb.jpg",
      "tracks": [
        {
          "number": 1,
          "name": "Won't Be Me",
          "duration": "3:34"
        }
      ]
    },
    {
      "name": "Wide Awake",
      "year": "2024",
      "release_date": "2024-11-28",
      "cover": "https://is1-ssl.mzstatic.com/image/thumb/Music221/v4/59/9f/b8/599fb8cd-c60d-be00-4ad0-5a8387dfcae9/287181.jpg/600x600bb.jpg",
      "tracks": [
        {
          "number": 1,
          "name": "Wide Awake",
          "duration": "2:59"
        }
      ]
    },
    {
      "name": "I Don't Like Me",
      "year": "2021",
      "release_date": "2021-09-10",
      "cover": "https://is1-ssl.mzstatic.com/image/thumb/Music125/v4/f1/87/0d/f1870d8c-d946-fed0-983a-2a4226761ac9/18571.jpg/600x600bb.jpg",
      "tracks": [
        {
          "number": 1,
          "name": "I Don't Like Me",
          "duration": "3:20"
        }
      ]
    },
    {
      "name": "Voices",
      "year": "2019",
      "release_date": "2019-07-15",
      "cover": "https://is1-ssl.mzstatic.com/image/thumb/Music123/v4/ed/d4/40/edd440ca-acd9-7871-f886-6cb81285ca4e/cover.jpg/600x600bb.jpg",
      "tracks": [
        {
          "number": 1,
          "name": "Voices",
          "duration": "2:58"
        }
      ]
    },
    {
      "name": "Same Old Story",
      "year": "2024",
      "release_date": "2024-08-15",
      "cover": "https://is1-ssl.mzstatic.com/image/thumb/Music211/v4/ae/f6/e4/aef6e4d5-d877-7daf-2ff5-c14f5a80d3b7/XEL25466.jpg/600x600bb.jpg",
      "tracks": [
        {
          "number": 1,
          "name": "Same Old Story",
          "duration": "2:24"
        }
      ]
    },
    {
      "name": "Wasting Time",
      "year": "2024",
      "release_date": "2024-06-13",
      "cover": "https://is1-ssl.mzstatic.com/image/thumb/Music221/v4/cf/47/00/cf47004a-43eb-67c0-8d1b-5ca68f3cb0a3/XEL25467.jpg/600x600bb.jpg",
      "tracks": [
        {
          "number": 1,
          "name": "Wasting Time",
          "duration": "3:04"
        },
        {
          "number": 2,
          "name": "Nothing to Lose",
          "duration": "2:24"
        }
      ]
    },
    {
      "name": "Let's Talk",
      "year": "2023",
      "release_date": "2023-06-23",
      "cover": "https://is1-ssl.mzstatic.com/image/thumb/Music116/v4/d4/64/98/d46498cd-cccb-0d56-b333-a4e784b59f6d/113807.jpg/600x600bb.jpg",
      "tracks": [
        {
          "number": 1,
          "name": "Let's Talk",
          "duration": "3:07"
        }
      ]
    },
    {
      "name": "Self Medicate",
      "year": "2021",
      "release_date": "2021-02-26",
      "cover": "https://is1-ssl.mzstatic.com/image/thumb/Music114/v4/0b/ea/b7/0beab740-0a31-deba-c6e9-5fb12249a123/8803.jpg/600x600bb.jpg",
      "tracks": [
        {
          "number": 1,
          "name": "Self Medicate",
          "duration": "2:35"
        }
      ]
    },
    {
      "name": "Prove Me Wrong",
      "year": "2021",
      "release_date": "2021-06-04",
      "cover": "https://is1-ssl.mzstatic.com/image/thumb/Music125/v4/4f/e8/7d/4fe87d01-7317-ae66-7366-57fe0c514c87/12977.jpg/600x600bb.jpg",
      "tracks": [
        {
          "number": 1,
          "name": "Prove Me Wrong",
          "duration": "3:23"
        }
      ]
    },
    {
      "name": "Drifter",
      "year": "2020",
      "release_date": "2020-03-27",
      "cover": "https://is1-ssl.mzstatic.com/image/thumb/Music123/v4/5f/b0/e4/5fb0e411-2f88-3313-d2b2-e5ee58d25ea4/4136.jpg/600x600bb.jpg",
      "tracks": [
        {
          "number": 1,
          "name": "Drifter",
          "duration": "2:52"
        }
      ]
    },
    {
      "name": "Fine Without You",
      "year": "2023",
      "release_date": "2023-04-28",
      "cover": "https://is1-ssl.mzstatic.com/image/thumb/Music126/v4/2e/dc/77/2edc7762-3d0d-c79f-9c4b-6a5793e8e629/96547.jpg/600x600bb.jpg",
      "tracks": [
        {
          "number": 1,
          "name": "Fine Without You",
          "duration": "2:46"
        }
      ]
    },
    {
      "name": "Anne Marie",
      "year": "2025",
      "release_date": "2025-05-30",
      "cover": "https://is1-ssl.mzstatic.com/image/thumb/Music221/v4/a8/cf/52/a8cf520c-6f3b-b317-00f7-f243094aecfa/XEL25453.jpg/600x600bb.jpg",
      "tracks": [
        {
          "number": 1,
          "name": "Anne Marie",
          "duration": "2:41"
        }
      ]
    },
    {
      "name": "One for You One for Me",
      "year": "2019",
      "release_date": "2019-04-01",
      "cover": "https://is1-ssl.mzstatic.com/image/thumb/Music123/v4/5f/50/87/5f5087cb-1ed3-4c1e-cb9c-7480d86705f8/859731479445_cover.jpg/600x600bb.jpg",
      "tracks": [
        {
          "number": 1,
          "name": "One for You One for Me",
          "duration": "2:41"
        }
      ]
    }
  ],
  "eps": [
    {
      "name": "But No Thanks",
      "year": "2020",
      "release_date": "2020-07-17",
      "cover": "https://is1-ssl.mzstatic.com/image/thumb/Music113/v4/40/2d/69/402d690f-2fa3-43fb-2ffe-1517a06edd94/5152.jpg/600x600bb.jpg",
      "tracks": [
        {
          "number": 1,
          "name": "Drifter",
          "duration": "2:52"
        },
        {
          "number": 2,
          "name": "Victims",
          "duration": "2:40"
        },
        {
          "number": 3,
          "name": "Falling Out",
          "duration": "3:29"
        },
        {
          "number": 4,
          "name": "Don't Forget",
          "duration": "3:29"
        },
        {
          "number": 5,
          "name": "Who Are We Now",
          "duration": "2:22"
        }
      ]
    },
    {
      "name": "For Nothing",
      "year": "2019",
      "release_date": "2019-07-22",
      "cover": "https://is1-ssl.mzstatic.com/image/thumb/Music123/v4/36/8b/7c/368b7cf3-61ef-f6ee-2069-ef87c3ecb9a8/cover.jpg/600x600bb.jpg",
      "tracks": [
        {
          "number": 1,
          "name": "One For You One For Me",
          "duration": "2:41"
        },
        {
          "number": 2,
          "name": "Voices",
          "duration": "2:58"
        },
        {
          "number": 3,
          "name": "Wastr",
          "duration": "3:58"
        },
        {
          "number": 4,
          "name": "Crossroads",
          "duration": "3:27"
        }
      ]
    },
    {
      "name": "Falling Is Pretty Normal",
      "year": "2022",
      "release_date": "2022-02-11",
      "cover": "https://is1-ssl.mzstatic.com/image/thumb/Music126/v4/88/42/23/8842235c-be4d-7c78-350d-c47bbc575cf6/35399.jpg/600x600bb.jpg",
      "tracks": [
        {
          "number": 1,
          "name": "Self Medicate",
          "duration": "2:35"
        },
        {
          "number": 2,
          "name": "Prove Me Wrong",
          "duration": "3:23"
        },
        {
          "number": 3,
          "name": "Falling Is Pretty Normal",
          "duration": "2:35"
        },
        {
          "number": 4,
          "name": "I Don't Like Me",
          "duration": "3:20"
        },
        {
          "number": 5,
          "name": "Won't Be Me",
          "duration": "3:34"
        }
      ]
    },
    {
      "name": "SOL DA MANHÃ",
      "year": "2026",
      "release_date": "2026-01-07",
      "cover": "https://is1-ssl.mzstatic.com/image/thumb/Music211/v4/40/ce/9d/40ce9d8a-feba-c587-99b1-34de59d66fe0/656465458643_cover.jpg/600x600bb.jpg",
      "tracks": [
        {
          "number": 1,
          "name": "SOL DA MANHÃ",
          "duration": "1:19"
        },
        {
          "number": 2,
          "name": "SOL DA MANHÃ (Slowed)",
          "duration": "1:28"
        },
        {
          "number": 3,
          "name": "SOL DA MANHÃ (Super Slowed)",
          "duration": "1:39"
        },
        {
          "number": 4,
          "name": "SOL DA MANHÃ (Sped Up)",
          "duration": "1:12"
        }
      ]
    },
    {
      "name": "Montagem Orchestral",
      "year": "2026",
      "release_date": "2026-03-06",
      "cover": "https://is1-ssl.mzstatic.com/image/thumb/Music211/v4/7b/10/6a/7b106aba-91f4-476a-75bd-8b90a86b5508/656465078360_cover.jpg/600x600bb.jpg",
      "tracks": [
        {
          "number": 1,
          "name": "Montagem Orchestral",
          "duration": "1:24"
        },
        {
          "number": 2,
          "name": "Montagem Orchestral (Slowed)",
          "duration": "1:46"
        },
        {
          "number": 3,
          "name": "Montagem Orchestral (Super Slowed)",
          "duration": "2:01"
        },
        {
          "number": 4,
          "name": "Montagem Orchestral (Sped Up)",
          "duration": "1:17"
        }
      ]
    },
    {
      "name": "MONTAGEM ENERGIA",
      "year": "2025",
      "release_date": "2025-12-17",
      "cover": "https://is1-ssl.mzstatic.com/image/thumb/Music221/v4/34/a5/86/34a586b2-c4f9-c8b6-87a2-00096122e8dd/656465436856_cover.jpg/600x600bb.jpg",
      "tracks": [
        {
          "number": 1,
          "name": "MONTAGEM ENERGIA",
          "duration": "1:15"
        },
        {
          "number": 2,
          "name": "MONTAGEM ENERGIA - Slowed",
          "duration": "1:24"
        },
        {
          "number": 3,
          "name": "MONTAGEM ENERGIA - Super Slowed",
          "duration": "1:34"
        },
        {
          "number": 4,
          "name": "MONTAGEM ENERGIA - Ultra Slowed",
          "duration": "1:46"
        },
        {
          "number": 5,
          "name": "MONTAGEM ENERGIA - Sped Up",
          "duration": "1:06"
        }
      ]
    }
  ]
}