{
  "name": "Grave Risk",
  "id": 1360660482,
  "albums": [],
  "singles": [
    {
      "name": "S.T.K. / Guts",
      "year": "2023",
      "release_date": "2023-03-03",
      "cover": "https://is1-ssl.mzstatic.com/image/thumb/Music116/v4/3f/d1/d3/3fd1d3ea-206b-cfa9-b6d6-d6ea9cd99562/197188220082.jpg/600x600bb.jpg",
      "tracks": [
        {
          "number": 1,
          "name": "S.T.K.",
          "duration": "2:22"
        },
        {
          "number": 2,
          "name": "Guts",
          "duration": "3:08"
        }
      ]
    },
    {
      "name": "Burn Away",
      "year": "2023",
      "release_date": "2023-09-15",
      "cover": "https://is1-ssl.mzstatic.com/image/thumb/Music116/v4/29/16/5e/29165e4e-1a90-503e-0ecc-0b6617a5ece7/197189614590.jpg/600x600bb.jpg",
      "tracks": [
        {
          "number": 1,
          "name": "Omega",
          "duration": "4:13"
        },
        {
          "number": 2,
          "name": "Burn Away",
          "duration": "3:27"
        },
        {
          "number": 3,
          "name": "Oblivion",
          "duration": "4:02"
        }
      ]
    },
    {
      "name": "Good For Me",
      "year": "2025",
      "release_date": "2025-02-21",
      "cover": "https://is1-ssl.mzstatic.com/image/thumb/Music211/v4/1d/b1/fe/1db1fe73-92ad-1e0d-bf45-8fa5850a9ad8/199066587782.jpg/600x600bb.jpg",
      "tracks": [
        {
          "number": 1,
          "name": "Good For Me",
          "duration": "1:34"
        }
      ]
    }
  ],
  "eps": [
    {
      "name": "Mindkiller",
      "year": "2024",
      "release_date": "2024-08-30",
      "cover": "https://is1-ssl.mzstatic.com/image/thumb/Music211/v4/8f/99/96/8f99962d-193d-84cd-0382-5f3a973147fe/198588716601.jpg/600x600bb.jpg",
      "tracks": [
        {
          "number": 1,
          "name": "Pain in Truth",
          "duration": "2:04"
        },
        {
          "number": 2,
          "name": "Mindkiller",
          "duration": "2:43"
        },
        {
          "number": 3,
          "name": "Forever Cursed",
          "duration": "1:50"
        },
        {
          "number": 4,
          "name": "Bonehead",
          "duration": "1:29"
        }
      ]
    }
  ]
}