{
  "name": "Lenaïg",
  "id": 1758705406,
  "albums": [
    {
      "name": "Éclair",
      "year": "2025",
      "release_date": "2025-11-28",
      "cover": "https://is1-ssl.mzstatic.com/image/thumb/Music221/v4/55/3f/aa/553faa7c-1de7-4b25-91bc-64f3f1ed30b2/cover.jpg/600x600bb.jpg",
      "tracks": [
        {
          "number": 1,
          "name": "J'veux que t'aies mal",
          "duration": "3:12"
        },
        {
          "number": 2,
          "name": "Je ne pense qu'à ça",
          "duration": "2:35"
        },
        {
          "number": 3,
          "name": "Du ferme",
          "duration": "2:54"
        },
        {
          "number": 4,
          "name": "Aussi simple que toi",
          "duration": "2:38"
        },
        {
          "number": 5,
          "name": "Internet",
          "duration": "3:10"
        },
        {
          "number": 6,
          "name": "Vas-y, aboie !",
          "duration": "2:18"
        },
        {
          "number": 7,
          "name": "Dans un autre univers",
          "duration": "2:42"
        }
      ]
    }
  ],
  "singles": [
    {
      "name": "Rien à carrer",
      "year": "2026",
      "release_date": "2026-04-24",
      "cover": "https://is1-ssl.mzstatic.com/image/thumb/Music221/v4/ea/6e/68/ea6e6812-cc7e-405e-410a-20f2af5a8c79/cover.jpg/600x600bb.jpg",
      "tracks": [
        {
          "number": 1,
          "name": "Rien à carrer",
          "duration": "2:48"
        }
      ]
    },
    {
      "name": "Je ne pense qu'à ça",
      "year": "2024",
      "release_date": "2024-11-15",
      "cover": "https://is1-ssl.mzstatic.com/image/thumb/Music221/v4/f2/96/02/f2960266-220a-36f1-1f5e-48360cfc87fd/cover.jpg/600x600bb.jpg",
      "tracks": [
        {
          "number": 1,
          "name": "Je ne pense qu'à ça",
          "duration": "2:35"
        },
        {
          "number": 2,
          "name": "Je ne pense qu'à ça (Acoustique)",
          "duration": "2:56"
        }
      ]
    },
    {
      "name": "Internet",
      "year": "2025",
      "release_date": "2025-04-11",
      "cover": "https://is1-ssl.mzstatic.com/image/thumb/Music211/v4/56/1d/0d/561d0d10-897b-ef5d-73f1-c1f1d3ec3579/cover.jpg/600x600bb.jpg",
      "tracks": [
        {
          "number": 1,
          "name": "Internet",
          "duration": "3:10"
        }
      ]
    },
    {
      "name": "Aussi simple que toi",
      "year": "2025",
      "release_date": "2025-08-22",
      "cover": "https://is1-ssl.mzstatic.com/image/thumb/Music221/v4/2f/26/05/2f2605f4-0c4a-68b4-579c-1fcedc081cc8/cover.jpg/600x600bb.jpg",
      "tracks": [
        {
          "number": 1,
          "name": "Aussi simple que toi",
          "duration": "2:38"
        }
      ]
    },
    {
      "name": "Vas-y, aboie !",
      "year": "2024",
      "release_date": "2024-08-30",
      "cover": "https://is1-ssl.mzstatic.com/image/thumb/Music221/v4/31/27/0f/31270f66-a59b-526e-7640-55ec2bb00160/cover.jpg/600x600bb.jpg",
      "tracks": [
        {
          "number": 1,
          "name": "Vas-y, aboie !",
          "duration": "2:18"
        }
      ]
    }
  ],
  "eps": [
    {
      "name": "Je ne pense qu'à ça",
      "year": "2025",
      "release_date": "2025-07-18",
      "cover": "https://is1-ssl.mzstatic.com/image/thumb/Music221/v4/52/e8/a7/52e8a7e9-1691-8797-c42a-94594f4f2f86/cover.jpg/600x600bb.jpg",
      "tracks": [
        {
          "number": 1,
          "name": "Je ne pense qu'à ça",
          "duration": "2:35"
        },
        {
          "number": 2,
          "name": "Du ferme",
          "duration": "2:54"
        },
        {
          "number": 3,
          "name": "Je ne pense qu'à ça (Rock Version)",
          "duration": "2:33"
        },
        {
          "number": 4,
          "name": "Je ne pense qu'à ça (Acoustique)",
          "duration": "2:56"
        }
      ]
    }
  ]
}