{
  "name": "MHD",
  "id": 1089789428,
  "albums": [
    {
      "name": "19",
      "year": "2018",
      "release_date": "2018-09-19",
      "cover": "https://is1-ssl.mzstatic.com/image/thumb/Music125/v4/bb/3b/a5/bb3ba54e-d6b0-7ca2-0475-37b3be89fad6/00602577004285.rgb.jpg/600x600bb.jpg",
      "tracks": [
        {
          "number": 1,
          "name": "Intro Mansa (feat. Salif Keita)",
          "duration": "1:55"
        },
        {
          "number": 2,
          "name": "Encore",
          "duration": "3:19"
        },
        {
          "number": 3,
          "name": "Rouler",
          "duration": "3:22"
        },
        {
          "number": 4,
          "name": "Bravo",
          "duration": "3:39"
        },
        {
          "number": 5,
          "name": "Le temps (feat. Orelsan)",
          "duration": "3:33"
        },
        {
          "number": 6,
          "name": "Papalé",
          "duration": "3:50"
        },
        {
          "number": 7,
          "name": "Fuego",
          "duration": "2:51"
        },
        {
          "number": 8,
          "name": "Bébé (feat. Dadju)",
          "duration": "4:05"
        },
        {
          "number": 9,
          "name": "Interlude trap 2",
          "duration": "1:56"
        },
        {
          "number": 10,
          "name": "Oh la la",
          "duration": "3:28"
        },
        {
          "number": 11,
          "name": "Bella (feat. Wizkid)",
          "duration": "3:03"
        },
        {
          "number": 12,
          "name": "Afro Trap Pt. 10 (Moula Gang)",
          "duration": "2:54"
        },
        {
          "number": 13,
          "name": "Samedi dimanche",
          "duration": "3:02"
        },
        {
          "number": 14,
          "name": "Feeling",
          "duration": "3:25"
        },
        {
          "number": 15,
          "name": "Aleo (feat. Yemi Alade)",
          "duration": "3:35"
        },
        {
          "number": 16,
          "name": "Porsche Panamera (feat. Koys)",
          "duration": "2:48"
        },
        {
          "number": 17,
          "name": "Moussa",
          "duration": "3:17"
        },
        {
          "number": 18,
          "name": "Senseless Ting (feat. Stefflon Don)",
          "duration": "3:10"
        },
        {
          "number": 19,
          "name": "XIX",
          "duration": "4:17"
        }
      ]
    },
    {
      "name": "MHD",
      "year": "2016",
      "release_date": "2016-04-15",
      "cover": "https://is1-ssl.mzstatic.com/image/thumb/Music128/v4/e8/f3/3a/e8f33aeb-f081-323d-46fe-957f8ba27ea9/00602547841155.rgb.jpg/600x600bb.jpg",
      "tracks": [
        {
          "number": 1,
          "name": "La Moula",
          "duration": "3:27"
        },
        {
          "number": 2,
          "name": "Afro Trap, Pt. 2 (Kakala Bomaye)",
          "duration": "2:05"
        },
        {
          "number": 3,
          "name": "Afro Trap, Pt. 3 (Champions League)",
          "duration": "2:17"
        },
        {
          "number": 4,
          "name": "Afro Trap, Pt. 4 (Fais le mouv)",
          "duration": "2:35"
        },
        {
          "number": 5,
          "name": "Mort ce soir",
          "duration": "3:22"
        },
        {
          "number": 6,
          "name": "A Kele Nta",
          "duration": "3:24"
        },
        {
          "number": 7,
          "name": "Afro Trap, Pt. 5 (Ngatie Abedi)",
          "duration": "2:34"
        },
        {
          "number": 8,
          "name": "Interlude Trap",
          "duration": "2:12"
        },
        {
          "number": 9,
          "name": "Amina",
          "duration": "3:24"
        },
        {
          "number": 10,
          "name": "Tout seul",
          "duration": "3:07"
        },
        {
          "number": 11,
          "name": "Afro Trap, Pt. 6 (Molo Molo)",
          "duration": "2:20"
        },
        {
          "number": 12,
          "name": "Ma vie (feat. Fally Ipupa)",
          "duration": "3:06"
        },
        {
          "number": 13,
          "name": "Roger Milla",
          "duration": "3:20"
        },
        {
          "number": 14,
          "name": "Maman j’ai mal",
          "duration": "3:23"
        },
        {
          "number": 15,
          "name": "Wanyinyin (feat. Angélique Kidjo)",
          "duration": "3:25"
        }
      ]
    },
    {
      "name": "MHD: Bzrp Music Sessions, Vol. 44/66",
      "year": "2021",
      "release_date": "2021-09-15",
      "cover": "https://is1-ssl.mzstatic.com/image/thumb/Music221/v4/0e/35/b2/0e35b2f1-1c52-823e-4d67-2a49a79d53fa/196292436464.jpg/600x600bb.jpg",
      "tracks": [
        {
          "number": 1,
          "name": "MHD: Bzrp Music Sessions, Vol. 44/66",
          "duration": "2:53"
        }
      ]
    },
    {
      "name": "Mansa",
      "year": "2021",
      "release_date": "2021-07-15",
      "cover": "https://is1-ssl.mzstatic.com/image/thumb/Music125/v4/e4/aa/b6/e4aab6f3-eefc-ce0a-2a38-56c1ce3331d7/21UMGIM57367.rgb.jpg/600x600bb.jpg",
      "tracks": []
    }
  ],
  "singles": [
    {
      "name": "Bella (feat. Wizkid)",
      "year": "2018",
      "release_date": "2018-07-19",
      "cover": "https://is1-ssl.mzstatic.com/image/thumb/Music128/v4/62/56/a9/6256a949-210c-a69d-cdc6-9328622fc068/00602567919032.rgb.jpg/600x600bb.jpg",
      "tracks": [
        {
          "number": 1,
          "name": "Bella (feat. Wizkid)",
          "duration": "3:05"
        }
      ]
    },
    {
      "name": "Laissez-les kouma (feat. MHD)",
      "year": "2016",
      "release_date": "2016-06-24",
      "cover": "https://is1-ssl.mzstatic.com/image/thumb/Music30/v4/fb/fd/e3/fbfde3d8-18a4-b94a-826f-3e3f5554b0b8/190295938949.jpg/600x600bb.jpg",
      "tracks": [
        {
          "number": 1,
          "name": "Laissez-les kouma (feat. MHD)",
          "duration": "3:16"
        }
      ]
    },
    {
      "name": "Tek Tek (feat. MHD)",
      "year": "2023",
      "release_date": "2023-05-12",
      "cover": "https://is1-ssl.mzstatic.com/image/thumb/Music116/v4/83/04/29/83042999-7b32-02ba-2db2-6e4ab92ee0b0/196871112956.jpg/600x600bb.jpg",
      "tracks": [
        {
          "number": 1,
          "name": "Tek Tek (feat. MHD)",
          "duration": "2:41"
        }
      ]
    },
    {
      "name": "Afro Trap Part. 7 (La puissance)",
      "year": "2016",
      "release_date": "2016-12-23",
      "cover": "https://is1-ssl.mzstatic.com/image/thumb/Music114/v4/05/67/aa/0567aa12-9485-72b9-4e1d-a719d1ec61fc/00602557391824.rgb.jpg/600x600bb.jpg",
      "tracks": [
        {
          "number": 1,
          "name": "Afro Trap Pt. 7 (La puissance)",
          "duration": "2:20"
        }
      ]
    },
    {
      "name": "Bodyguard",
      "year": "2018",
      "release_date": "2018-06-19",
      "cover": "https://is1-ssl.mzstatic.com/image/thumb/Music115/v4/7d/ee/b3/7deeb373-2f57-4604-be80-a63c6339aa23/00602567803126.rgb.jpg/600x600bb.jpg",
      "tracks": [
        {
          "number": 1,
          "name": "Bodyguard",
          "duration": "2:44"
        }
      ]
    },
    {
      "name": "Direction ÉTERNEL INSATISFAIT épisode 2 : A l'ouest (feat. MHD)",
      "year": "2016",
      "release_date": "2016-07-22",
      "cover": "https://is1-ssl.mzstatic.com/image/thumb/Music18/v4/a0/5c/ed/a05ced30-585c-5a64-5d3b-ded499741150/886445917185.jpg/600x600bb.jpg",
      "tracks": [
        {
          "number": 1,
          "name": "Direction ETERNEL INSATISFAIT épisode 2 : A l'ouest (feat. MHD)",
          "duration": "4:21"
        }
      ]
    },
    {
      "name": "Gaga (feat. MHD)",
      "year": "2022",
      "release_date": "2022-07-01",
      "cover": "https://is1-ssl.mzstatic.com/image/thumb/Music122/v4/e3/41/ce/e341ce8b-6e45-c26e-0424-1a715b66481a/196589270795.jpg/600x600bb.jpg",
      "tracks": [
        {
          "number": 1,
          "name": "Gaga (feat. MHD)",
          "duration": "3:44"
        }
      ]
    },
    {
      "name": "Kata",
      "year": "2024",
      "release_date": "2024-09-13",
      "cover": "https://is1-ssl.mzstatic.com/image/thumb/Music221/v4/be/3c/6f/be3c6fde-bcf3-b3a9-2692-0323fb379bfd/859794026822_cover.jpg/600x600bb.jpg",
      "tracks": [
        {
          "number": 1,
          "name": "Kata",
          "duration": "2:16"
        }
      ]
    },
    {
      "name": "Afro Trap, Pt. 8 (Never)",
      "year": "2017",
      "release_date": "2017-02-24",
      "cover": "https://is1-ssl.mzstatic.com/image/thumb/Music118/v4/50/1d/6f/501d6fd7-041f-0721-e5e9-62cd7b580258/00602557410631.rgb.jpg/600x600bb.jpg",
      "tracks": [
        {
          "number": 1,
          "name": "Afro Trap, Pt. 8 (Never)",
          "duration": "2:29"
        }
      ]
    },
    {
      "name": "Lyca",
      "year": "2023",
      "release_date": "2023-08-04",
      "cover": "https://is1-ssl.mzstatic.com/image/thumb/Music126/v4/8b/ea/ec/8beaec94-833c-ff10-6725-4b76552659a0/859776399135_cover.jpg/600x600bb.jpg",
      "tracks": [
        {
          "number": 1,
          "name": "Lyca",
          "duration": "2:34"
        }
      ]
    },
    {
      "name": "In Da Car",
      "year": "2022",
      "release_date": "2022-08-04",
      "cover": "https://is1-ssl.mzstatic.com/image/thumb/Music122/v4/a9/37/bc/a937bc7c-ff20-17eb-6349-9b43e2dea2e1/196925409292.jpg/600x600bb.jpg",
      "tracks": [
        {
          "number": 1,
          "name": "In Da Car",
          "duration": "4:18"
        }
      ]
    },
    {
      "name": "Afro Trap Pt. 10 (Moula Gang)",
      "year": "2018",
      "release_date": "2018-01-26",
      "cover": "https://is1-ssl.mzstatic.com/image/thumb/Music118/v4/a8/73/a5/a873a572-76ba-cf5f-ceb6-600ab4d8097e/00602567422235.rgb.jpg/600x600bb.jpg",
      "tracks": [
        {
          "number": 1,
          "name": "Afro Trap Pt. 10 (Moula Gang)",
          "duration": "2:54"
        }
      ]
    },
    {
      "name": "DX3 (Dégâts X3)",
      "year": "2024",
      "release_date": "2024-12-20",
      "cover": "https://is1-ssl.mzstatic.com/image/thumb/Music221/v4/27/67/27/2767275a-3a72-7a3b-fc50-4d43f990dd13/24UM1IM40659.rgb.jpg/600x600bb.jpg",
      "tracks": []
    },
    {
      "name": "Intro Mansa (feat. Salif Keïta)",
      "year": "2018",
      "release_date": "2018-08-22",
      "cover": "https://is1-ssl.mzstatic.com/image/thumb/Music118/v4/79/09/4d/79094dac-42f4-95bc-1982-4018bcfe2bbf/00602577016202.rgb.jpg/600x600bb.jpg",
      "tracks": [
        {
          "number": 1,
          "name": "Intro Mansa (feat. Salif Keïta)",
          "duration": "1:55"
        }
      ]
    },
    {
      "name": "WDMD",
      "year": "2024",
      "release_date": "2024-11-15",
      "cover": "https://is1-ssl.mzstatic.com/image/thumb/Music221/v4/aa/c2/14/aac214c0-1b3b-2365-c8af-04c196da8c94/3663729348630_cover.jpg/600x600bb.jpg",
      "tracks": [
        {
          "number": 1,
          "name": "WDMD",
          "duration": "2:25"
        }
      ]
    },
    {
      "name": "B L A C K C A R D",
      "year": "2021",
      "release_date": "2021-11-19",
      "cover": "https://is1-ssl.mzstatic.com/image/thumb/Music126/v4/7f/cb/f9/7fcbf924-b826-cf97-752c-cef289727e4c/cover.jpg/600x600bb.jpg",
      "tracks": [
        {
          "number": 1,
          "name": "B L A C K C A R D",
          "duration": "3:15"
        }
      ]
    },
    {
      "name": "Afro Trap, Pt. 7 (La puissance) [Major Lazer Remix]",
      "year": "2018",
      "release_date": "2018-01-15",
      "cover": "https://is1-ssl.mzstatic.com/image/thumb/Music128/v4/e3/57/39/e3573965-0ae0-16a9-2072-d9e66ee56efc/00602567397717.rgb.jpg/600x600bb.jpg",
      "tracks": []
    },
    {
      "name": "Bravo",
      "year": "2017",
      "release_date": "2017-06-17",
      "cover": "https://is1-ssl.mzstatic.com/image/thumb/Music128/v4/9e/5f/c9/9e5fc97c-9b32-5760-8fdb-c8142453696c/00602557799002.rgb.jpg/600x600bb.jpg",
      "tracks": [
        {
          "number": 1,
          "name": "Bravo",
          "duration": "3:41"
        }
      ]
    },
    {
      "name": "Turn Up (feat. Leto & MHD)",
      "year": "2024",
      "release_date": "2024-08-09",
      "cover": "https://is1-ssl.mzstatic.com/image/thumb/Music221/v4/5b/69/d9/5b69d94b-fde2-73ee-cd46-2c9e52d3facb/196872319446.jpg/600x600bb.jpg",
      "tracks": [
        {
          "number": 1,
          "name": "Turn Up (feat. Leto & MHD)",
          "duration": "2:25"
        }
      ]
    },
    {
      "name": "Bénéfice",
      "year": "2018",
      "release_date": "2018-03-09",
      "cover": "https://is1-ssl.mzstatic.com/image/thumb/Music128/v4/bc/5b/6c/bc5b6c07-2446-07e2-d3de-e8b79f77cf9a/190295656393.jpg/600x600bb.jpg",
      "tracks": []
    },
    {
      "name": "Fire (feat. Felo Le Tee & Mellow and Sleazy) [Radio Edit]",
      "year": "2023",
      "release_date": "2023-06-30",
      "cover": "https://is1-ssl.mzstatic.com/image/thumb/Music211/v4/b5/b7/80/b5b7808d-b4af-9e73-e0ac-251f4bf2cf5d/757572948130.jpg/600x600bb.jpg",
      "tracks": [
        {
          "number": 1,
          "name": "Fire (feat. Felo Le Tee & Mellow and Sleazy) [Radio Edit]",
          "duration": "3:25"
        }
      ]
    },
    {
      "name": "Eyla",
      "year": "2025",
      "release_date": "2025-01-17",
      "cover": "https://is1-ssl.mzstatic.com/image/thumb/Music221/v4/46/60/cf/4660cf26-a3b3-ac91-800c-24564bbd2573/196056579659_cover.jpg/600x600bb.jpg",
      "tracks": [
        {
          "number": 1,
          "name": "Eyla",
          "duration": "2:38"
        }
      ]
    },
    {
      "name": "Full",
      "year": "2024",
      "release_date": "2024-08-02",
      "cover": "https://is1-ssl.mzstatic.com/image/thumb/Music221/v4/28/88/c9/2888c927-3e8f-1cd4-938e-82e9faddf5a5/859791762976_cover.jpg/600x600bb.jpg",
      "tracks": [
        {
          "number": 1,
          "name": "Full",
          "duration": "2:28"
        }
      ]
    },
    {
      "name": "Pololo (feat. Tiakola)",
      "year": "2021",
      "release_date": "2021-07-09",
      "cover": "https://is1-ssl.mzstatic.com/image/thumb/Music115/v4/9a/b9/ac/9ab9ac67-7781-3380-5a7c-770a394fd2a3/21UMGIM57367.rgb.jpg/600x600bb.jpg",
      "tracks": []
    },
    {
      "name": "I WISH",
      "year": "2024",
      "release_date": "2024-10-16",
      "cover": "https://is1-ssl.mzstatic.com/image/thumb/Music211/v4/fb/0e/4c/fb0e4ca2-1eb6-613d-9e42-0ef8361cc657/cover.jpg/600x600bb.jpg",
      "tracks": [
        {
          "number": 1,
          "name": "I WISH",
          "duration": "2:38"
        }
      ]
    },
    {
      "name": "Le S",
      "year": "2025",
      "release_date": "2025-01-17",
      "cover": "https://is1-ssl.mzstatic.com/image/thumb/Music221/v4/7a/fb/40/7afb404b-8dd1-6045-4a6c-3dc14595966b/196056684131_cover.jpg/600x600bb.jpg",
      "tracks": [
        {
          "number": 1,
          "name": "Le S",
          "duration": "2:12"
        }
      ]
    },
    {
      "name": "Afro Trap Part. 11 (King Kong)",
      "year": "2021",
      "release_date": "2021-05-27",
      "cover": "https://is1-ssl.mzstatic.com/image/thumb/Music115/v4/3d/4f/e6/3d4fe6cf-8991-ff14-a5d7-2c873e372789/21UMGIM46433.rgb.jpg/600x600bb.jpg",
      "tracks": []
    },
    {
      "name": "Eiffel Tower",
      "year": "2024",
      "release_date": "2024-10-25",
      "cover": "https://is1-ssl.mzstatic.com/image/thumb/Music221/v4/93/f8/33/93f833a7-8f38-6dae-001f-390a26c2a4b3/859796296636_cover.jpg/600x600bb.jpg",
      "tracks": [
        {
          "number": 1,
          "name": "Eiffel Tower",
          "duration": "2:28"
        }
      ]
    },
    {
      "name": "Jungle",
      "year": "2023",
      "release_date": "2023-08-25",
      "cover": "https://is1-ssl.mzstatic.com/image/thumb/Music126/v4/a8/d3/f1/a8d3f16c-232b-5075-a2ac-1faed3a02cdf/859777369335_cover.jpg/600x600bb.jpg",
      "tracks": [
        {
          "number": 1,
          "name": "Jungle",
          "duration": "2:24"
        }
      ]
    },
    {
      "name": "Afro Trap Pt. 9 (Faut les wet)",
      "year": "2017",
      "release_date": "2017-07-18",
      "cover": "https://is1-ssl.mzstatic.com/image/thumb/Music128/v4/77/5f/ff/775fffe2-e9ba-6a2c-4feb-000c8439a3b5/00602557899375.rgb.jpg/600x600bb.jpg",
      "tracks": [
        {
          "number": 1,
          "name": "Afro Trap Pt. 9 (Faut les wet)",
          "duration": "2:35"
        }
      ]
    },
    {
      "name": "DX3 (Dégâts X3)",
      "year": "2024",
      "release_date": "2024-12-20",
      "cover": "https://is1-ssl.mzstatic.com/image/thumb/Music221/v4/0f/00/a6/0f00a6a3-3b28-8179-cf30-c0d4668defec/24UM1IM40659.rgb.jpg/600x600bb.jpg",
      "tracks": []
    }
  ],
  "eps": [
    {
      "name": "Afro Trap (Mad Decent Remixes)",
      "year": "2018",
      "release_date": "2018-02-02",
      "cover": "https://is1-ssl.mzstatic.com/image/thumb/Music221/v4/f9/c4/72/f9c47254-bd5e-de1f-e4a1-448e802a7b48/733.jpg/600x600bb.jpg",
      "tracks": [
        {
          "number": 1,
          "name": "Afro Trap, Pt. 7 (La Puissance) [Major Lazer Remix]",
          "duration": "3:10"
        },
        {
          "number": 2,
          "name": "Afro Trap, Pt. 3 (Champions League) [TroyBoi Remix]",
          "duration": "3:19"
        },
        {
          "number": 3,
          "name": "Bravo (VERSANO Remix)",
          "duration": "3:43"
        },
        {
          "number": 4,
          "name": "Bravo (Rawtek Remix)",
          "duration": "3:20"
        }
      ]
    }
  ]
}